Workbook
Name _2_Way_FIBER_RF_Upgrade_Cost_Per_Mile: Assumptions!$B$102
Name _2_Way_Miles_per_Subscriber: Assumptions!$B$103
Name Acquired_Subscribers: Assumptions!$G$6:$L$6
Name Acquisition_Cost_per_subscriber: Assumptions!$G$7:$L$7
Name Advertising_Revenue_per_Sub: Assumptions!$B$107
Name Annual_Reduction_Starting_Year_2: Assumptions!$B$52
Name AR_DOH: Assumptions!$E$10
Name ARPU_Cable: Assumptions!$B$7
Name ARPU_Data: Assumptions!$B$14
Name ARPU_Voice: Assumptions!$B$22
Name ARPU_Voice_Data: Assumptions!$B$23
Name Assets_Acquired_per_Acquisition: Assumptions!$H$13
Name Attrition_Data: Assumptions!$B$15
Name Attrition_Voice: Assumptions!$B$24
Name Cable_Attrition: Assumptions!$B$8
Name Cable_Customer_Acquisition_Cost: Assumptions!$B$9
Name Carrier_Interconnections: Assumptions!$B$57
Name CMTS_Cost_Per_Subscriber: Assumptions!$B$63
Name CMTS_Initial_Capacity_Subs: Assumptions!$B$64
Name CMTS_Initial_Cost: Assumptions!$B$62
Name CMTS_Max_Capacity_Subs: Assumptions!$B$65
Name Commissions_Sales_and_Collections: OPEX!$B$81
Name cost_International_Calls: Assumptions!$B$41
Name Cost_Local_Termination_Off_Net: Assumptions!$B$40
Name Cost_per_Data_Trunk: Assumptions!$B$58
Name Cost_per_Household_Cabling: Assumptions!$B$93
Name Cost_per_Subscriber_Cable: Assumptions!$B$51
Name Cost_per_Voice_Trunk: Assumptions!$B$59
Name Cost_Roaming_Other_Net: Assumptions!$B$42
Name Cost_to_individual_Home: Assumptions!$B$94
Name CPE_Cable_Modem: Assumptions!$B$78
Name CPE_Router: Assumptions!$B$80
Name CPE_Voice_Adaptor: Assumptions!$B$79
Name Data_Customer_Acquisition_cost: Assumptions!$B$16
Name Data_Subscribers_Trunk: Assumptions!$B$55
Name Depreciation_Life_Months: Assumptions!$B$105
Name Edge_Router_Cost: Assumptions!$B$73
Name Edge_Router_Subs: Assumptions!$B$72
Name Ethernet_Radios: Assumptions!$B$86
Name Existing_Subscribers: Assumptions!#REF!
Name Fiber_Cost_per_Mile: Assumptions!$B$71
Name Fiber_Start: Assumptions!$B$99
Name Increase_per_Year: Assumptions!$B$47
Name Installation_Fee_Cable: Assumptions!$B$10
Name Local_Termination_On_Net: Assumptions!$B$43
Name Long_fiber_Cost: Assumptions!$B$97
Name Miles_Long_Fiber: Assumptions!$B$98
Name Minutes_International_Minutes: Assumptions!$B$31
Name Minutes_Roaming: Assumptions!$B$30
Name Minutes_Terminating_Off_Net: Assumptions!$B$32
Name Organic_Sub_Adds: Assumptions!$G$10:$L$10
Name Penetration_per_Households: Assumptions!$B$92
Name Rev_Minute_Roaming: Assumptions!$B$36
Name Rev_Minutes_International_Calls: Assumptions!$B$37
Name Soft_Switch_Cost_Per_Subscriber: Assumptions!$B$67
Name Soft_Switch_Initial_Payment: Assumptions!$B$66
Name Soft_Switch_Maintenance_per_Year: Assumptions!$B$68
Name Subs_Terminating_On_Net: Assumptions!$B$33
Name Termination_Minutes_Subscriber: Assumptions!$B$46
Name Termination_Revenue_Minute: Assumptions!$B$48

Sheet Sources & Uses
B4: Sources and Uses
B5: Sources | C5: US$ | E5: Uses | F5: US$
B6: Line of Credit | C6: 0 | E6: Purchase of XXX | F6: ='Financial Statements & Detail'!C238 -> 5500000
B7: Term Loan | C7: 0 | E7: Startup Equipment | F7: ='Financial Statements & Detail'!C243-'Financial Statements & Detail'!C236 -> 3310158
B8: Mezzanine Debt | C8: 0 | E8: Telecom License | F8: =Assumptions!B88 -> 2000000
B9: Shares for Company Acquired | C9: ='Financial Statements & Detail'!C241 -> 2750000 | E9: Working Capital | F9: 4000000
B10: New Equity | C10: =F11-SUM(C6:C9) -> 12560158 | E10: Closing Costs | F10: 500000
B11: Total | C11: =SUM(C6:C10) -> 15310158 | E11: Total | F11: =SUM(F6:F10) -> 15310158
B13: Values in Blue are from assumptions elsewhere in model; changes on this page to blue values have no affect on model
B14: Values in Black are Hacker's assumptions and flow through the model
B17: Debt financing for subsequent years is on "Financial Statements" tab Row 246
B18: Debt drawdowns row 248 needs to be manually adjusted to change cash position
B20: Assumptions throughout the model are in blue and are included in the Assumptions and OPEX tabs;
B21: a few assumptions are on the Financial Statements tab
B23: Summary Financials and Return Calculations are on the Assumptions Tab
B25: Model is not formatted for printing

Sheet Assumptions
A2: Assumptions, Summary Financials, Return Calculations
A3: US$
G5: Year | H5: 1 | I5: 2 | J5: 3 | K5: 4 | L5: 5
A6: Cable Service | G6: Acquired Subscribers | H6: 11000 | I6: 25000 | J6: 25000 | K6: =J6 -> 25000 | L6: =K6 -> 25000
A7: ARPU | B7: 14.5 | G7: Cost per Subscriber Acquired | H7: 500 | I7: =H7 -> 500 | J7: =I7 -> 500 | K7: =J7 -> 500 | L7: =K7 -> 500
A8: % Attrition | B8: 0.03
A9: Customer Acquisition Cost | B9: 5 | G9: Organic Growth % | H9: 0.3 | I9: 0.3 | J9: 0.2 | K9: =J9 -> 0.2 | L9: =K9 -> 0.2
A10: Installation Fee | B10: 0 | D10: AR DOH | E10: 45 | G10: Organic Sub Adds | H10: =H9*SUM(G$6:$H6) -> 3300 | I10: =I9*SUM($H$6:H6) -> 3300 | J10: =J9*SUM($H$6:I6) -> 7200 | K10: =K9*SUM($H$6:J6) -> 12200 | L10: =L9*SUM($H$6:K6) -> 17200
D11: AP DOH | E11: 30 | G11: New Households Passed | H11: =H10/$B$92 -> 9428.5714 | I11: =I10/$B$92 -> 9428.5714 | J11: =J10/$B$92 -> 20571.429 | K11: =K10/$B$92 -> 34857.143 | L11: =L10/$B$92 -> 49142.857
A12: Data Service
A13: % with Data | B13: 0.35 | G13: Net Asset Value Acquired per Acquisition | H13: 1500000
A14: ARPU | B14: 40 | G14: Purchase Price Paid in New Stock | H14: 0.5
A15: % Attrition | B15: 0.01
A16: Customer Acquisition cost | B16: 5
G18: Financial Summary
A19: Voice Service | H19: 2008 | I19: 2009 | J19: 2010 | K19: 2011 | L19: 2012
A20: % with Voice & Data | B20: 0.2 | H20: 12 Mos. | I20: 12 Mos. | J20: 12 Mos. | K20: 12 Mos. | L20: 12 Mos.
A21: % with Voice | B21: 0.25 | G21: US$ | H21: Forecast | I21: Forecast | J21: Forecast | K21: Forecast | L21: Forecast
A22: ARPU Voice | B22: 20 | G22: Net Sales Revenue | H22: =SUM('Financial Statements & Detail'!C7:N7) -> 6646054.4 | I22: =SUM('Financial Statements & Detail'!O7:Z7) -> 15112344 | J22: =SUM('Financial Statements & Detail'!AA7:AL7) -> 24606907 | K22: =SUM('Financial Statements & Detail'!AM7:AX7) -> 33275575 | L22: =SUM('Financial Statements & Detail'!AY7:BJ7) -> 41637140
A23: ARPU Voice/Data | B23: =ARPU_Data+ARPU_Voice-10 -> 50 | G23: Gross Profit | H23: =SUM('Financial Statements & Detail'!C9:N9) -> 1455661.7 | I23: =SUM('Financial Statements & Detail'!O9:Z9) -> 3714097.3 | J23: =SUM('Financial Statements & Detail'!AA9:AL9) -> 7988762.2 | K23: =SUM('Financial Statements & Detail'!AM9:AX9) -> 12167563 | L23: =SUM('Financial Statements & Detail'!AY9:BJ9) -> 16200254
A24: Attrition | B24: 0.025 | G24: Operating Expenses | H24: =SUM('Financial Statements & Detail'!C29:N29) -> 1751202.9 | I24: =SUM('Financial Statements & Detail'!O29:Z29) -> 2190930.3 | J24: =SUM('Financial Statements & Detail'!AA29:AL29) -> 2671888.7 | K24: =SUM('Financial Statements & Detail'!AM29:AX29) -> 3264436.4 | L24: =SUM('Financial Statements & Detail'!AY29:BJ29) -> 4201056.7
A25: Customer Acquisition cost | B25: 10 | G25: Operating Income | H25: =SUM('Financial Statements & Detail'!C31:N31) -> -295541.16 | I25: =SUM('Financial Statements & Detail'!O31:Z31) -> 1523167 | J25: =SUM('Financial Statements & Detail'!AA31:AL31) -> 5316873.5 | K25: =SUM('Financial Statements & Detail'!AM31:AX31) -> 8903126.9 | L25: =SUM('Financial Statements & Detail'!AY31:BJ31) -> 11999197
A26: Existing Subscribers | B26: 0 | G26: Interest Expense | H26: =SUM('Financial Statements & Detail'!C34:N34) -> 0 | I26: =SUM('Financial Statements & Detail'!O34:Z34) -> 1411666.7 | J26: =SUM('Financial Statements & Detail'!AA34:AL34) -> 2371875 | K26: =SUM('Financial Statements & Detail'!AM34:AX34) -> 2497105 | L26: =SUM('Financial Statements & Detail'!AY34:BJ34) -> 2476045.4
G27: Pre-Tax Income | H27: =SUM('Financial Statements & Detail'!C37:N37) -> -295541.16 | I27: =SUM('Financial Statements & Detail'!O37:Z37) -> 111500.36 | J27: =SUM('Financial Statements & Detail'!AA37:AL37) -> 2944998.5 | K27: =SUM('Financial Statements & Detail'!AM37:AX37) -> 6406021.9 | L27: =SUM('Financial Statements & Detail'!AY37:BJ37) -> 9523151.7
A28: Voice Minutes Subscriber/Month | G28: EBITDA | H28: =SUM('Financial Statements & Detail'!C41:N41) -> 766227.76 | I28: =SUM('Financial Statements & Detail'!O41:Z41) -> 4802456.6 | J28: =SUM('Financial Statements & Detail'!AA41:AL41) -> 10303491 | K28: =SUM('Financial Statements & Detail'!AM41:AX41) -> 15776083 | L28: =SUM('Financial Statements & Detail'!AY41:BJ41) -> 20995276
A29: Total Call Minutes per Month | B29: 400
A30: Subs_Roaming Other Networks Minutes | B30: 1e-06 | G30: % Growth Revenue | H30: na | I30: =I22/H22-1 -> 1.2738821 | J30: =J22/I22-1 -> 0.62826544 | K30: =K22/J22-1 -> 0.35228595 | L30: =L22/K22-1 -> 0.25128235
A31: Subs-International Minutes | B31: 40 | G31: % Gross Profit/Revenue | H31: =H23/H22 -> 0.21902645 | I31: =I23/I22 -> 0.2457658 | J31: =J23/J22 -> 0.32465527 | K31: =K23/K22 -> 0.3656605 | L31: =L23/L22 -> 0.38908181
A32: Subs-Terminating Off Net Minutes | B32: =B29*0.8 -> 320 | G32: % EBITDA/Revenue | H32: =H28/H22 -> 0.11529062 | I32: =I28/I22 -> 0.3177837 | J32: =J28/J22 -> 0.41872354 | K32: =K28/K22 -> 0.47410401 | L32: =L28/L22 -> 0.50424396
A33: Subs-Terminating On Net Minutes | B33: =B29-Minutes_International_Minutes-Minutes_Terminating_Off_Net -> 40
G34: Accounts Receivable | H34: ='Financial Statements & Detail'!N47 -> 898814.59 | I34: ='Financial Statements & Detail'!Z47 -> 2221391 | J34: ='Financial Statements & Detail'!AL47 -> 3338039.6 | K34: ='Financial Statements & Detail'!AX47 -> 4401318 | L34: ='Financial Statements & Detail'!BJ47 -> 5432450.2
A35: Voice Revenue/Minute | G35: Inventory | H35: ='Financial Statements & Detail'!N48 -> 456008.98 | I35: ='Financial Statements & Detail'!Z48 -> 352651.91 | J35: ='Financial Statements & Detail'!AL48 -> 363385.97 | K35: ='Financial Statements & Detail'!AX48 -> 395197.53 | L35: ='Financial Statements & Detail'!BJ48 -> 484828.9
A36: Subs_Roaming Other Networks | B36: =Minutes_Roaming -> 1e-06 | G36: Working Capital | H36: ='Financial Statements & Detail'!N89 -> 3779935.3 | I36: ='Financial Statements & Detail'!Z89 -> 2938564.3 | J36: ='Financial Statements & Detail'!AL89 -> 3863780.1 | K36: ='Financial Statements & Detail'!AX89 -> 2865333.1 | L36: ='Financial Statements & Detail'!BJ89 -> 4940948.4
A37: Subs-International Calls | B37: 0.1 | G37: PP&E | H37: ='Financial Statements & Detail'!N56 -> 4734681.5 | I37: ='Financial Statements & Detail'!Z56 -> 14545444 | J37: ='Financial Statements & Detail'!AL56 -> 18436387 | K37: ='Financial Statements & Detail'!AX56 -> 21522269 | L37: ='Financial Statements & Detail'!BJ56 -> 23704067
A39: Voice Minute Costs | G39: AR & Inventory Financing | H39: ='Financial Statements & Detail'!N64 -> 0 | I39: ='Financial Statements & Detail'!Z64 -> 0 | J39: ='Financial Statements & Detail'!AL64 -> 0 | K39: ='Financial Statements & Detail'!AX64 -> 0 | L39: ='Financial Statements & Detail'!BJ64 -> 0
A40: Local Termination-Off Net | B40: 0.02 | G40: Total Funded Debt | H40: ='Financial Statements & Detail'!N91 -> 0 | I40: ='Financial Statements & Detail'!Z91 -> 14000000 | J40: ='Financial Statements & Detail'!AL91 -> 20500000 | K40: ='Financial Statements & Detail'!AX91 -> 20302083 | L40: ='Financial Statements & Detail'!BJ91 -> 20118273
A41: International Calls | B41: 0.008 | G41: Related Party Debt | H41: ='Financial Statements & Detail'!N73 -> 0 | I41: ='Financial Statements & Detail'!Z73 -> 0 | J41: ='Financial Statements & Detail'!AL73 -> 0 | K41: ='Financial Statements & Detail'!AX73 -> 0 | L41: ='Financial Statements & Detail'!BJ73 -> 0
A42: Roaming Other Net | B42: 0.015 | G42: Total Debt | H42: =SUM(H39:H41) -> 0 | I42: =SUM(I39:I41) -> 14000000 | J42: =SUM(J39:J41) -> 20500000 | K42: =SUM(K39:K41) -> 20302083 | L42: =SUM(L39:L41) -> 20118273
A43: Local Termination-On Net | B43: =IF(B88>0,0,0.009) -> 0 | G43: Equity | H43: ='Financial Statements & Detail'!N84 -> 15014617 | I43: ='Financial Statements & Detail'!Z84 -> 21192342 | J43: ='Financial Statements & Detail'!AL84 -> 29356591 | K43: ='Financial Statements & Detail'!AX84 -> 39770505 | L43: ='Financial Statements & Detail'!BJ84 -> 52210554
A45: Termination Revenue Non-subscribers | G45: Current Ratio | H45: ='Financial Statements & Detail'!N90 -> 11.048707 | I45: ='Financial Statements & Detail'!Z90 -> 1.833624 | J45: ='Financial Statements & Detail'!AL90 -> 1.7046557 | K45: ='Financial Statements & Detail'!AX90 -> 1.4966766 | L45: ='Financial Statements & Detail'!BJ90 -> 1.8256522
A46: Minutes/Subscriber | B46: 5 | G46: Debt/Equity Ratio | H46: ='Financial Statements & Detail'!N92 -> 0 | I46: ='Financial Statements & Detail'!Z92 -> 0.660616 | J46: ='Financial Statements & Detail'!AL92 -> 0.69830997 | K46: ='Financial Statements & Detail'!AX92 -> 0.5104809 | L46: ='Financial Statements & Detail'!BJ92 -> 0.38532962
A47: Increase per Year | B47: 0.2 | G47: Total Debt/EBITDA Annualized | H47: =H42/H28 -> 0 | I47: =I42/I28 -> 2.9151747 | J47: =J42/J28 -> 1.9896168 | K47: =K42/K28 -> 1.28689 | L47: =L42/L28 -> 0.95822852
A48: Revenue/Minute | B48: 0.02 | G48: EBITDA/Interest Expense | H48: =H28/H26 -> #DIV/0! | I48: =I28/I26 -> 3.4019763 | J48: =J28/J26 -> 4.344028 | K48: =K28/K26 -> 6.3177492 | L48: =L28/L26 -> 8.4793585
A50: Cable Content
A51: Cost per Subscriber | B51: 15
A52: Annual Reduction Starting Year 2 | B52: 0.2
A54: Trunks
A55: Data Subscribers/Trunk E-1 | B55: 10000
A56: Voice subscribers/Trunk E-1 | B56: 5000
A57: Carrier Interconnections Voice | B57: 4
A58: Cost per Data Trunk | B58: 1500
A59: Cost per Voice Trunk | B59: 1500
A61: CAPEX
A62: Voice CMTS Initial Cost | B62: 250000
A63: CMTS Cost Per Subscriber | B63: 20
A64: CMTS Initial Capacity Subs | B64: 4000
A65: CMTS Max Capacity Subs | B65: 40000
A66: Soft Switch Initial Payment | B66: 75000
A67: Soft Switch Cost Per Subscriber | B67: 80
A68: Soft Switch Maintenance per Year | B68: 200000
A69: Voice Mail Server | B69: 200000
A70: Voice Provisioning System | B70: 200000
A72: Edge Router/Subs | B72: 1000
A73: Edge Router Cost | B73: 10000
A74: Core Routers | B74: 2
A75: Core Router Cost | B75: 25000
A77: Customer Premise Equipment
A78: CPE-Cable Modem | B78: 50
A79: CPE-Voice Adaptor | B79: 25
A80: CPE-Router | B80: 25
A82: CAPEX Headend
A83: Voicemail | B83: 200000
A84: Provisioning | B84: 200000
A85: Miscellaneous Equipment | B85: 200000
A86: Ethernet Radios | B86: 0
A87: Billing system | B87: 300000
A88: Telecom License | B88: 2000000
A89: Miscellaneous Costs | B89: 1000000
A91: Subscriber Construction Cost
A92: Penetration per Households | B92: 0.35
A93: Cost per Household | B93: 55
A94: Cost to individual Home | B94: 40
A96: Long Run Fiber
A97: Long fiber | B97: 92000
A98: Miles | B98: 50
A99: Start date | B99: 39814
A101: 2 Way Fiber/RF Cost
A102: 2 Way FIBER/RF Upgrade Cost Per Mile | B102: 4000
A103: 2 Way Miles per Subscriber | B103: =100/11000 -> 0.0090909091
A105: Depreciation Life Months | B105: 60
A107: Advertising Revenue per Sub | B107: 1

Sheet Financial Statements & Detail
A2: P&L, Balance Sheet, Debt Schedule
A3: Revenue and COS Detail
A4: US$
A5: Debt Schedule Row 246 | C5: 1 | D5: 1 | E5: 1 | F5: 1 | G5: 1 | H5: 1 | I5: 1 | J5: 1 | K5: 1 | L5: 1 | M5: 1 | N5: 1 | O5: 2 | P5: 2 | Q5: 2 | R5: 2 | S5: 2 | T5: 2 | U5: 2 | V5: 2 | W5: 2 | X5: 2 | Y5: 2 | Z5: 2 | AA5: 3 | AB5: 3 | AC5: 3 | AD5: 3 | AE5: 3 | AF5: 3 | AG5: 3 | AH5: 3 | AI5: 3 | AJ5: 3 | AK5: 3 | AL5: 3 | AM5: 4 | AN5: 4 | AO5: 4 | AP5: 4 | AQ5: 4 | AR5: 4 | AS5: 4 | AT5: 4 | AU5: 4 | AV5: 4 | AW5: 4 | AX5: 4 | AY5: 5 | AZ5: 5 | BA5: 5 | BB5: 5 | BC5: 5 | BD5: 5 | BE5: 5 | BF5: 5 | BG5: 5 | BH5: 5 | BI5: 5 | BJ5: 5
C6: 39455 | D6: 39486 | E6: 39515 | F6: 39546 | G6: 39576 | H6: 39607 | I6: 39637 | J6: 39668 | K6: 39699 | L6: 39729 | M6: 39760 | N6: 39790 | O6: 39821 | P6: 39852 | Q6: 39880 | R6: 39911 | S6: 39941 | T6: 39972 | U6: 40002 | V6: 40033 | W6: 40064 | X6: 40094 | Y6: 40125 | Z6: 40155 | AA6: 40186 | AB6: 40217 | AC6: 40245 | AD6: 40276 | AE6: 40306 | AF6: 40337 | AG6: 40367 | AH6: 40398 | AI6: 40429 | AJ6: 40459 | AK6: 40490 | AL6: 40520 | AM6: 40551 | AN6: 40582 | AO6: 40610 | AP6: 40641 | AQ6: 40671 | AR6: 40702 | AS6: 40732 | AT6: 40763 | AU6: 40794 | AV6: 40824 | AW6: 40855 | AX6: 40885 | AY6: 40916 | AZ6: 40947 | BA6: 40976 | BB6: 41007 | BC6: 41037 | BD6: 41068 | BE6: 41098 | BF6: 41129 | BG6: 41160 | BH6: 41190 | BI6: 41221 | BJ6: 41251
A7: Revenue | C7: =C139 -> 503622.63 | D7: =D139 -> 513695.08 | E7: =E139 -> 523465.36 | F7: =F139 -> 532942.53 | G7: =G139 -> 542135.38 | H7: =H139 -> 551052.45 | I7: =I139 -> 559702.01 | J7: =J139 -> 568092.08 | ... BJ7: =BJ139 -> 3621633.5
A8: Cost of Sales | C8: =C176 -> 391354.63 | D8: =D176 -> 398631.82 | E8: =E176 -> 411531.1 | F8: =F176 -> 418265.87 | G8: =G176 -> 424841.08 | H8: =H176 -> 431261.51 | I8: =I176 -> 437531.81 | J8: =J176 -> 443656.47 | ... BJ8: =BJ176 -> 2248484.6
A9: Gross Margin | C9: =C7-C8 -> 112268 | D9: =D7-D8 -> 115063.26 | E9: =E7-E8 -> 111934.26 | F9: =F7-F8 -> 114676.65 | G9: =G7-G8 -> 117294.3 | H9: =H7-H8 -> 119790.94 | I9: =I7-I8 -> 122170.2 | J9: =J7-J8 -> 124435.61 | ... BJ9: =BJ7-BJ8 -> 1373148.9
A11: Operating Expenses
A12: Advertising & Promotion | C12: =OPEX!C12 -> 79420 | D12: =OPEX!D12 -> 2935.9 | E12: =OPEX!E12 -> 2889.073 | F12: =OPEX!F12 -> 2843.6508 | G12: =OPEX!G12 -> 2799.5913 | H12: =OPEX!H12 -> 2756.8535 | I12: =OPEX!I12 -> 2715.3979 | J12: =OPEX!J12 -> 2675.186 | ... BJ12: =OPEX!BJ12 -> 7166.6667
A13: Auto | C13: =OPEX!C13 -> 0 | D13: =OPEX!D13 -> 0 | E13: =OPEX!E13 -> 0 | F13: =OPEX!F13 -> 0 | G13: =OPEX!G13 -> 0 | H13: =OPEX!H13 -> 0 | I13: =OPEX!I13 -> 0 | J13: =OPEX!J13 -> 0 | ... BJ13: =OPEX!BJ13 -> 0
A14: Bad Debts | C14: =OPEX!C14 -> 0 | D14: =OPEX!D14 -> 0 | E14: =OPEX!E14 -> 0 | F14: =OPEX!F14 -> 0 | G14: =OPEX!G14 -> 0 | H14: =OPEX!H14 -> 0 | I14: =OPEX!I14 -> 0 | J14: =OPEX!J14 -> 0 | ... BJ14: =OPEX!BJ14 -> 0
A15: Bank Service Charges | C15: =OPEX!C15 -> 0 | D15: =OPEX!D15 -> 0 | E15: =OPEX!E15 -> 0 | F15: =OPEX!F15 -> 0 | G15: =OPEX!G15 -> 0 | H15: =OPEX!H15 -> 0 | I15: =OPEX!I15 -> 0 | J15: =OPEX!J15 -> 0 | ... BJ15: =OPEX!BJ15 -> 0
A16: Consultants | C16: =OPEX!C16 -> 0 | D16: =OPEX!D16 -> 0 | E16: =OPEX!E16 -> 0 | F16: =OPEX!F16 -> 0 | G16: =OPEX!G16 -> 0 | H16: =OPEX!H16 -> 0 | I16: =OPEX!I16 -> 0 | J16: =OPEX!J16 -> 0 | ... BJ16: =OPEX!BJ16 -> 0
A17: Employee Benefits | C17: =OPEX!C17 -> 13946.25 | D17: =OPEX!D17 -> 13983.75 | E17: =OPEX!E17 -> 13983.75 | F17: =OPEX!F17 -> 14021.25 | G17: =OPEX!G17 -> 14021.25 | H17: =OPEX!H17 -> 14178.75 | I17: =OPEX!I17 -> 14216.25 | J17: =OPEX!J17 -> 14216.25 | ... BJ17: =OPEX!BJ17 -> 24448.75
A18: Equipment Leases | C18: =OPEX!C18 -> 0 | D18: =OPEX!D18 -> 0 | E18: =OPEX!E18 -> 0 | F18: =OPEX!F18 -> 0 | G18: =OPEX!G18 -> 0 | H18: =OPEX!H18 -> 0 | I18: =OPEX!I18 -> 0 | J18: =OPEX!J18 -> 0 | ... BJ18: =OPEX!BJ18 -> 0
A19: Insurance | C19: =OPEX!C19 -> 0 | D19: =OPEX!D19 -> 0 | E19: =OPEX!E19 -> 0 | F19: =OPEX!F19 -> 0 | G19: =OPEX!G19 -> 0 | H19: =OPEX!H19 -> 0 | I19: =OPEX!I19 -> 0 | J19: =OPEX!J19 -> 0 | ... BJ19: =OPEX!BJ19 -> 0
A20: Legal | C20: =OPEX!C20 -> 0 | D20: =OPEX!D20 -> 0 | E20: =OPEX!E20 -> 0 | F20: =OPEX!F20 -> 0 | G20: =OPEX!G20 -> 0 | H20: =OPEX!H20 -> 0 | I20: =OPEX!I20 -> 0 | J20: =OPEX!J20 -> 0 | ... BJ20: =OPEX!BJ20 -> 0
A21: Office Rent | C21: =OPEX!C21 -> 10000 | D21: =OPEX!D21 -> 10000 | E21: =OPEX!E21 -> 10000 | F21: =OPEX!F21 -> 10000 | G21: =OPEX!G21 -> 10000 | H21: =OPEX!H21 -> 10000 | I21: =OPEX!I21 -> 10000 | J21: =OPEX!J21 -> 10000 | ... BJ21: =OPEX!BJ21 -> 80000
A22: Office Supplies | C22: =OPEX!C22 -> 1500 | D22: =OPEX!D22 -> 1500 | E22: =OPEX!E22 -> 1500 | F22: =OPEX!F22 -> 1500 | G22: =OPEX!G22 -> 1500 | H22: =OPEX!H22 -> 1500 | I22: =OPEX!I22 -> 1500 | J22: =OPEX!J22 -> 1500 | ... BJ22: =OPEX!BJ22 -> 24000
A23: Professional Fees | B23: Summary Financials and Return Calculations are on the Assumptions Tab | C23: =OPEX!C23 -> 2000 | D23: =OPEX!D23 -> 2000 | E23: =OPEX!E23 -> 2000 | F23: =OPEX!F23 -> 2000 | G23: =OPEX!G23 -> 2000 | H23: =OPEX!H23 -> 2000 | I23: =OPEX!I23 -> 2000 | J23: =OPEX!J23 -> 2000 | ... BJ23: =OPEX!BJ23 -> 6000
A24: Salaries | C24: =OPEX!C24 -> 92975 | D24: =OPEX!D24 -> 93225 | E24: =OPEX!E24 -> 93225 | F24: =OPEX!F24 -> 93475 | G24: =OPEX!G24 -> 93475 | H24: =OPEX!H24 -> 94525 | I24: =OPEX!I24 -> 94775 | J24: =OPEX!J24 -> 94775 | ... BJ24: =OPEX!BJ24 -> 162991.67
A25: Subscription/Membership | C25: =OPEX!C25 -> 0 | D25: =OPEX!D25 -> 0 | E25: =OPEX!E25 -> 0 | F25: =OPEX!F25 -> 0 | G25: =OPEX!G25 -> 0 | H25: =OPEX!H25 -> 0 | I25: =OPEX!I25 -> 0 | J25: =OPEX!J25 -> 0 | ... BJ25: =OPEX!BJ25 -> 0
A26: Telephone | C26: =OPEX!C26 -> 0 | D26: =OPEX!D26 -> 0 | E26: =OPEX!E26 -> 0 | F26: =OPEX!F26 -> 0 | G26: =OPEX!G26 -> 0 | H26: =OPEX!H26 -> 0 | I26: =OPEX!I26 -> 0 | J26: =OPEX!J26 -> 0 | ... BJ26: =OPEX!BJ26 -> 0
A27: Travel & Entertainmnet | C27: =OPEX!C27 -> 5000 | D27: =OPEX!D27 -> 5000 | E27: =OPEX!E27 -> 5000 | F27: =OPEX!F27 -> 5000 | G27: =OPEX!G27 -> 5000 | H27: =OPEX!H27 -> 5000 | I27: =OPEX!I27 -> 5000 | J27: =OPEX!J27 -> 5000 | ... BJ27: =OPEX!BJ27 -> 25312.5
A28: Other | C28: =OPEX!C28 -> 10000 | D28: =OPEX!D28 -> 10000 | E28: =OPEX!E28 -> 10000 | F28: =OPEX!F28 -> 10000 | G28: =OPEX!G28 -> 10000 | H28: =OPEX!H28 -> 10000 | I28: =OPEX!I28 -> 10000 | J28: =OPEX!J28 -> 10000 | ... BJ28: =OPEX!BJ28 -> 10000
A29: Total | C29: =SUM(C12:C28) -> 214841.25 | D29: =SUM(D12:D28) -> 138644.65 | E29: =SUM(E12:E28) -> 138597.82 | F29: =SUM(F12:F28) -> 138839.9 | G29: =SUM(G12:G28) -> 138795.84 | H29: =SUM(H12:H28) -> 139960.6 | I29: =SUM(I12:I28) -> 140206.65 | J29: =SUM(J12:J28) -> 140166.44 | ... BJ29: =SUM(BJ12:BJ28) -> 339919.58
A31: Operating Income | C31: =C9-C29 -> -102573.25 | D31: =D9-D29 -> -23581.395 | E31: =E9-E29 -> -26663.564 | F31: =F9-F29 -> -24163.246 | G31: =G9-G29 -> -21501.54 | H31: =H9-H29 -> -20169.663 | I31: =I9-I29 -> -18036.445 | J31: =J9-J29 -> -15730.826 | ... BJ31: =BJ9-BJ29 -> 1033229.3
A33: Other Expenses
A34: Interest Expense | C34: =C258 -> 0 | D34: =D258 -> 0 | E34: =E258 -> 0 | F34: =F258 -> 0 | G34: =G258 -> 0 | H34: =H258 -> 0 | I34: =I258 -> 0 | J34: =J258 -> 0 | ... BJ34: =BJ258 -> 188377.35
A35: Total | C35: =C34 -> 0 | D35: =D34 -> 0 | E35: =E34 -> 0 | F35: =F34 -> 0 | G35: =G34 -> 0 | H35: =H34 -> 0 | I35: =I34 -> 0 | J35: =J34 -> 0 | ... BJ35: =BJ34 -> 188377.35
A37: Income Before Taxes | C37: =C31-C35 -> -102573.25 | D37: =D31-D35 -> -23581.395 | E37: =E31-E35 -> -26663.564 | F37: =F31-F35 -> -24163.246 | G37: =G31-G35 -> -21501.54 | H37: =H31-H35 -> -20169.663 | I37: =I31-I35 -> -18036.445 | J37: =J31-J35 -> -15730.826 | ... BJ37: =BJ31-BJ35 -> 844851.95
A38: Income Taxes | B38: 0.35 | C38: =MAX(C37*0.35,0) -> 0 | D38: =MAX(D37*0.35,0) -> 0 | E38: =MAX(E37*0.35,0) -> 0 | F38: =MAX(F37*0.35,0) -> 0 | G38: =MAX(G37*0.35,0) -> 0 | H38: =MAX(H37*0.35,0) -> 0 | I38: =MAX(I37*0.35,0) -> 0 | J38: =MAX(J37*0.35,0) -> 0 | ... BJ38: =MAX(BJ37*0.35,0) -> 295698.18
A39: Net Income | C39: =C37-C38 -> -102573.25 | D39: =D37-D38 -> -23581.395 | E39: =E37-E38 -> -26663.564 | F39: =F37-F38 -> -24163.246 | G39: =G37-G38 -> -21501.54 | H39: =H37-H38 -> -20169.663 | I39: =I37-I38 -> -18036.445 | J39: =J37-J38 -> -15730.826 | ... BJ39: =BJ37-BJ38 -> 549153.77
A41: EBITDA | C41: =C31+C244 -> -22403.95 | D41: =D31+D244 -> 58271.375 | E41: =E31+E244 -> 56694.486 | F41: =F31+F244 -> 60688.909 | G41: =G31+G244 -> 64833.879 | H41: =H31+H244 -> 67638.503 | I41: =I31+I244 -> 71234.269 | J41: =J31+J244 -> 74992.541 | ... BJ41: =BJ31+BJ244 -> 1848242.3
A43: Balance Sheet
A44: Assets
A45: Current Assets
A46: Cash | C46: =Cashflow!C41 -> 3179582.7 | D46: =Cashflow!D41 -> 3083639 | E46: =Cashflow!E41 -> 3035337.8 | F46: =Cashflow!F41 -> 2992285.7 | G46: =Cashflow!G41 -> 2954312.5 | H46: =Cashflow!H41 -> 2920792.9 | I46: =Cashflow!I41 -> 2891423 | J46: =Cashflow!J41 -> 2866651.1 | ... BJ46: =Cashflow!BJ41 -> 5007966.9
A47: Accounts Receivable | C47: =C247 -> 755433.94 | D47: =D247 -> 770542.62 | E47: =E247 -> 785198.03 | F47: =F247 -> 799413.79 | G47: =G247 -> 813203.07 | H47: =H247 -> 826578.68 | I47: =I247 -> 839553.01 | J47: =J247 -> 852138.12 | ... BJ47: =BJ247 -> 5432450.2
A48: Inventory | C48: =C248 -> 191924.09 | D48: =D248 -> 191491.37 | E48: =E248 -> 191071.63 | F48: =F248 -> 190664.48 | G48: =G248 -> 190269.55 | H48: =H248 -> 189886.46 | I48: =I248 -> 189514.87 | J48: =J248 -> 189154.42 | ... BJ48: =BJ248 -> 484828.9
A49: Prepaid Expenses | C49: 0 | D49: 0 | E49: 0 | F49: 0 | G49: 0 | H49: 0 | I49: 0 | J49: 0 | K49: 0 | L49: 0 | M49: 0 | N49: 0 | O49: 0 | P49: 0 | Q49: 0 | R49: 0 | S49: 0 | T49: 0 | U49: 0 | V49: 0 | W49: 0 | X49: 0 | Y49: 0 | Z49: 0 | AA49: 0 | AB49: 0 | AC49: 0 | AD49: 0 | AE49: 0 | AF49: 0 | AG49: 0 | AH49: 0 | AI49: 0 | AJ49: 0 | AK49: 0 | AL49: 0 | AM49: 0 | AN49: 0 | AO49: 0 | AP49: 0 | AQ49: 0 | AR49: 0 | AS49: 0 | AT49: 0 | AU49: 0 | AV49: 0 | AW49: 0 | AX49: 0 | AY49: 0 | AZ49: 0 | BA49: 0 | BB49: 0 | BC49: 0 | BD49: 0 | BE49: 0 | BF49: 0 | BG49: 0 | BH49: 0 | BI49: 0 | BJ49: 0
A50: Total Current Assets | C50: =SUM(C46:C49) -> 4126940.8 | D50: =SUM(D46:D49) -> 4045673 | E50: =SUM(E46:E49) -> 4011607.4 | F50: =SUM(F46:F49) -> 3982364 | G50: =SUM(G46:G49) -> 3957785.1 | H50: =SUM(H46:H49) -> 3937258 | I50: =SUM(I46:I49) -> 3920490.9 | J50: =SUM(J46:J49) -> 3907943.7 | ... BJ50: =SUM(BJ46:BJ49) -> 10925246
A52: Property, Plant & Equipment
A53: Property
A54: Plant & Equipment | C54: =C243 -> 4810158 | D54: =D243 -> 4911166.2 | E54: =E243 -> 5001483 | F54: =F243 -> 5091129.3 | G54: =G243 -> 5180125.1 | H54: =H243 -> 5268490 | I54: =I243 -> 5356242.8 | J54: =J243 -> 5443402 | ... BJ54: =BJ243 -> 48900779
A55: Accumulated Depreciation | C55: =C245 -> 80169.301 | D55: =D245 -> 162022.07 | E55: =E245 -> 245380.12 | F55: =F245 -> 330232.28 | G55: =G245 -> 416567.69 | H55: =H245 -> 504375.86 | I55: =I245 -> 593646.58 | J55: =J245 -> 684369.94 | ... BJ55: =BJ245 -> 25196712
A56: Net PP&E | C56: =C53+C54-C55 -> 4729988.7 | D56: =D53+D54-D55 -> 4749144.1 | E56: =E53+E54-E55 -> 4756102.9 | F56: =F53+F54-F55 -> 4760897 | G56: =G53+G54-G55 -> 4763557.4 | H56: =H53+H54-H55 -> 4764114.1 | I56: =I53+I54-I55 -> 4762596.2 | J56: =J53+J54-J55 -> 4759032.1 | ... BJ56: =BJ53+BJ54-BJ55 -> 23704067
A58: Other Assets | C58: =C232+C240+'Sources & Uses'!$F$10 -> 6500000 | D58: =D232+D240+'Sources & Uses'!$F$10 -> 6500000 | E58: =E232+E240+'Sources & Uses'!$F$10 -> 6500000 | F58: =F232+F240+'Sources & Uses'!$F$10 -> 6500000 | G58: =G232+G240+'Sources & Uses'!$F$10 -> 6500000 | H58: =H232+H240+'Sources & Uses'!$F$10 -> 6500000 | I58: =I232+I240+'Sources & Uses'!$F$10 -> 6500000 | J58: =J232+J240+'Sources & Uses'!$F$10 -> 6500000 | ... BJ58: =BJ232+BJ240+'Sources & Uses'!$F$10 -> 38500000
A60: Total Assets | C60: =C50+C56+C58 -> 15356930 | D60: =D50+D56+D58 -> 15294817 | E60: =E50+E56+E58 -> 15267710 | F60: =F50+F56+F58 -> 15243261 | G60: =G50+G56+G58 -> 15221343 | H60: =H50+H56+H58 -> 15201372 | I60: =I50+I56+I58 -> 15183087 | J60: =J50+J56+J58 -> 15166976 | ... BJ60: =BJ50+BJ56+BJ58 -> 73129313
A62: Liabilities & Shareholders Equity
A63: Current Liabilities
A64: Line of Credit
A65: CPLTD | C65: =C256 -> 0 | D65: =D256 -> 0 | E65: =E256 -> 0 | F65: =F256 -> 0 | G65: =G256 -> 0 | H65: =H256 -> 0 | I65: =I256 -> 0 | J65: =J256 -> 0 | ... BJ65: =BJ256 -> 5183810.8
A66: Accounts Payable | C66: =C249 -> 41924.094 | D66: =D249 -> 41491.371 | E66: =E249 -> 41071.63 | F66: =F249 -> 40664.481 | G66: =G249 -> 40269.546 | H66: =H249 -> 39886.46 | I66: =I249 -> 39514.866 | J66: =J249 -> 39154.42 | ... BJ66: =BJ249 -> 334828.9
A67: Accrued Expenses | C67: =0.5*C29 -> 107420.62 | D67: =0.5*D29 -> 69322.325 | E67: =0.5*E29 -> 69298.912 | F67: =0.5*F29 -> 69419.95 | G67: =0.5*G29 -> 69397.921 | H67: =0.5*H29 -> 69980.302 | I67: =0.5*I29 -> 70103.324 | J67: =0.5*J29 -> 70083.218 | ... BJ67: =0.5*BJ29 -> 169959.79
A68: Income Taxes Payable | C68: =C38 -> 0 | D68: =D38 -> 0 | E68: =E38 -> 0 | F68: =F38 -> 0 | G68: =G38 -> 0 | H68: =H38 -> 0 | I68: =I38 -> 0 | J68: =J38 -> 0 | ... BJ68: =BJ38 -> 295698.18
A69: Total Current Liabilities | C69: =SUM(C64:C68) -> 149344.72 | D69: =SUM(D64:D68) -> 110813.7 | E69: =SUM(E64:E68) -> 110370.54 | F69: =SUM(F64:F68) -> 110084.43 | G69: =SUM(G64:G68) -> 109667.47 | H69: =SUM(H64:H68) -> 109866.76 | I69: =SUM(I64:I68) -> 109618.19 | J69: =SUM(J64:J68) -> 109237.64 | ... BJ69: =SUM(BJ64:BJ68) -> 5984297.6
A71: Long Term Liabilities
A72: Long Term Debt | C72: =C257 -> 0 | D72: =D257 -> 0 | E72: =E257 -> 0 | F72: =F257 -> 0 | G72: =G257 -> 0 | H72: =H257 -> 0 | I72: =I257 -> 0 | J72: =J257 -> 0 | ... BJ72: =BJ257 -> 14934462
A73: Due to Shareholders
A74: Total Long Term Liabilities | C74: =SUM(C72:C73) -> 0 | D74: =SUM(D72:D73) -> 0 | E74: =SUM(E72:E73) -> 0 | F74: =SUM(F72:F73) -> 0 | G74: =SUM(G72:G73) -> 0 | H74: =SUM(H72:H73) -> 0 | I74: =SUM(I72:I73) -> 0 | J74: =SUM(J72:J73) -> 0 | ... BJ74: =SUM(BJ72:BJ73) -> 14934462
A75: Total Liabilities | C75: =C69+C74 -> 149344.72 | D75: =D69+D74 -> 110813.7 | E75: =E69+E74 -> 110370.54 | F75: =F69+F74 -> 110084.43 | G75: =G69+G74 -> 109667.47 | H75: =H69+H74 -> 109866.76 | I75: =I69+I74 -> 109618.19 | J75: =J69+J74 -> 109237.64 | ... BJ75: =BJ69+BJ74 -> 20918759
A77: Stockholders' Equity / (Deficit):
A78: Common Stock | C78: =SUM($C$241:C241)+'Sources & Uses'!$C$10 -> 15310158 | D78: =SUM($C$241:D241)+'Sources & Uses'!$C$10 -> 15310158 | E78: =SUM($C$241:E241)+'Sources & Uses'!$C$10 -> 15310158 | F78: =SUM($C$241:F241)+'Sources & Uses'!$C$10 -> 15310158 | G78: =SUM($C$241:G241)+'Sources & Uses'!$C$10 -> 15310158 | H78: =SUM($C$241:H241)+'Sources & Uses'!$C$10 -> 15310158 | I78: =SUM($C$241:I241)+'Sources & Uses'!$C$10 -> 15310158 | J78: =SUM($C$241:J241)+'Sources & Uses'!$C$10 -> 15310158 | ... BJ78: =SUM($C$241:BJ241)+'Sources & Uses'!$C$10 -> 40310158
A79: Preferred Series A
A80: Preferred Series B & D
A81: Additional Paid in Capital
A82: Retained Earnings/(Deficit) | C82: 0 | D82: =C82+C83 -> -102573.25 | E82: =D82+D83 -> -126154.65 | F82: =E82+E83 -> -152818.21 | G82: =F82+F83 -> -176981.46 | H82: =G82+G83 -> -198483 | I82: =H82+H83 -> -218652.66 | J82: =I82+I83 -> -236689.1 | K82: =J82+J83 -> -252419.93 | ... BJ82: =BI82+BI83 -> 11351242
A83: Net Income / (Loss) | C83: =C39 -> -102573.25 | D83: =D39 -> -23581.395 | E83: =E39 -> -26663.564 | F83: =F39 -> -24163.246 | G83: =G39 -> -21501.54 | H83: =H39 -> -20169.663 | I83: =I39 -> -18036.445 | J83: =J39 -> -15730.826 | ... BJ83: =BJ39 -> 549153.77
A84: Total Stockholders' Equity / (Deficit) | C84: =SUM(C78:C83) -> 15207585 | D84: =SUM(D78:D83) -> 15184003 | E84: =SUM(E78:E83) -> 15157340 | F84: =SUM(F78:F83) -> 15133177 | G84: =SUM(G78:G83) -> 15111675 | H84: =SUM(H78:H83) -> 15091505 | I84: =SUM(I78:I83) -> 15073469 | J84: =SUM(J78:J83) -> 15057738 | ... BJ84: =SUM(BJ78:BJ83) -> 52210554
A86: Total Liabilities and Stockholders' Equity / (Deficit) | C86: =C75+C84 -> 15356930 | D86: =D75+D84 -> 15294817 | E86: =E75+E84 -> 15267710 | F86: =F75+F84 -> 15243261 | G86: =G75+G84 -> 15221343 | H86: =H75+H84 -> 15201372 | I86: =I75+I84 -> 15183087 | J86: =J75+J84 -> 15166976 | ... BJ86: =BJ75+BJ84 -> 73129313
A88: Check Total | C88: =C60-C86 -> 0 | D88: =D60-D86 -> 0 | E88: =E60-E86 -> 0 | F88: =F60-F86 -> 0 | G88: =G60-G86 -> 0 | H88: =H60-H86 -> 0 | I88: =I60-I86 -> 0 | J88: =J60-J86 -> 0 | ... BJ88: =BJ60-BJ86 -> 0
A89: Working Capital | C89: =C50-C69 -> 3977596 | D89: =D50-D69 -> 3934859.3 | E89: =E50-E69 -> 3901236.9 | F89: =F50-F69 -> 3872279.5 | G89: =G50-G69 -> 3848117.6 | H89: =H50-H69 -> 3827391.3 | I89: =I50-I69 -> 3810872.7 | J89: =J50-J69 -> 3798706 | ... BJ89: =BJ50-BJ69 -> 4940948.4
A90: Current Ratio | C90: =C50/C69 -> 27.633657 | D90: =D50/D69 -> 36.508781 | E90: =E50/E69 -> 36.346723 | F90: =F50/F69 -> 36.175542 | G90: =G50/G69 -> 36.088962 | H90: =H50/H69 -> 35.836662 | I90: =I50/I69 -> 35.764966 | J90: =J50/J69 -> 35.774699 | ... BJ90: =BJ50/BJ69 -> 1.8256522
A91: Funded Debt | C91: =C64+C65+C72 -> 0 | D91: =D64+D65+D72 -> 0 | E91: =E64+E65+E72 -> 0 | F91: =F64+F65+F72 -> 0 | G91: =G64+G65+G72 -> 0 | H91: =H64+H65+H72 -> 0 | I91: =I64+I65+I72 -> 0 | J91: =J64+J65+J72 -> 0 | ... BJ91: =BJ64+BJ65+BJ72 -> 20118273
A92: Funded Debt/Equity | C92: =C91/C84 -> 0 | D92: =D91/D84 -> 0 | E92: =E91/E84 -> 0 | F92: =F91/F84 -> 0 | G92: =G91/G84 -> 0 | H92: =H91/H84 -> 0 | I92: =I91/I84 -> 0 | J92: =J91/J84 -> 0 | ... BJ92: =BJ91/BJ84 -> 0.38532962
A93: Funded Debt/EBITDA Annualized | C93: =C91/(C41*12) -> 0 | D93: =D91/(D41*12) -> 0 | E93: =E91/(E41*12) -> 0 | F93: =F91/(F41*12) -> 0 | G93: =G91/(G41*12) -> 0 | H93: =H91/(H41*12) -> 0 | I93: =I91/(I41*12) -> 0 | J93: =J91/(J41*12) -> 0 | ... BJ93: =BJ91/(BJ41*12) -> 0.90709033
A95: Detail
A96: Revenue
A97: Acq. Subscribers Cable
A98: Opening Subscribers | C98: =Assumptions!H6 -> 11000 | D98: =C101 -> 10945 | E98: =D101 -> 10891.65 | F98: =E101 -> 10839.9 | G98: =F101 -> 10789.703 | H98: =G101 -> 10741.012 | I98: =H101 -> 10693.782 | J98: =I101 -> 10647.969 | K98: =J101 -> 10603.529 | ... BJ98: =BI101 -> 53321.826
A99: Additions | O99: =VLOOKUP(Assumptions!$G$6,Acquired_Subscribers,'Financial Statements & Detail'!O5+1)/3 -> 8333.3333 | P99: =Assumptions!$F$14/12 -> 0 | R99: =VLOOKUP(Assumptions!$G$6,Acquired_Subscribers,'Financial Statements & Detail'!R5+1)/3 -> 8333.3333 | U99: =VLOOKUP(Assumptions!$G$6,Acquired_Subscribers,'Financial Statements & Detail'!U5+1)/3 -> 8333.3333 | AA99: =VLOOKUP(Assumptions!$G$6,Acquired_Subscribers,'Financial Statements & Detail'!AA5+1)/3 -> 8333.3333 | AD99: =VLOOKUP(Assumptions!$G$6,Acquired_Subscribers,'Financial Statements & Detail'!AD5+1)/3 -> 8333.3333 | AG99: =VLOOKUP(Assumptions!$G$6,Acquired_Subscribers,'Financial Statements & Detail'!AG5+1)/3 -> 8333.3333 | AM99: =VLOOKUP(Assumptions!$G$6,Acquired_Subscribers,'Financial Statements & Detail'!AM5+1)/3 -> 8333.3333 | AP99: =VLOOKUP(Assumptions!$G$6,Acquired_Subscribers,'Financial Statements & Detail'!AP5+1)/3 -> 8333.3333 | AS99: =VLOOKUP(Assumptions!$G$6,Acquired_Subscribers,'Financial Statements & Detail'!AS5+1)/3 -> 8333.3333 | AY99: =VLOOKUP(Assumptions!$G$6,Acquired_Subscribers,'Financial Statements & Detail'!AY5+1)/3 -> 8333.3333 | BB99: =VLOOKUP(Assumptions!$G$6,Acquired_Subscribers,'Financial Statements & Detail'!BB5+1)/3 -> 8333.3333 | BE99: =VLOOKUP(Assumptions!$G$6,Acquired_Subscribers,'Financial Statements & Detail'!BE5+1)/3 -> 8333.3333
A100: Attrition | C100: =Cable_Attrition*'Financial Statements & Detail'!C98 -> 330 | D100: =Cable_Attrition*'Financial Statements & Detail'!D98 -> 328.35 | E100: =Cable_Attrition*'Financial Statements & Detail'!E98 -> 326.7495 | F100: =Cable_Attrition*'Financial Statements & Detail'!F98 -> 325.19701 | G100: =Cable_Attrition*'Financial Statements & Detail'!G98 -> 323.6911 | H100: =Cable_Attrition*'Financial Statements & Detail'!H98 -> 322.23037 | I100: =Cable_Attrition*'Financial Statements & Detail'!I98 -> 320.81346 | J100: =Cable_Attrition*'Financial Statements & Detail'!J98 -> 319.43906 | ... BJ100: =Cable_Attrition*'Financial Statements & Detail'!BJ98 -> 1599.6548
A101: Ending | C101: =C98+C105-C100 -> 10945 | D101: =D98+D105-D100 -> 10891.65 | E101: =E98+E105-E100 -> 10839.9 | F101: =F98+F105-F100 -> 10789.703 | G101: =G98+G105-G100 -> 10741.012 | H101: =H98+H105-H100 -> 10693.782 | I101: =I98+I105-I100 -> 10647.969 | J101: =J98+J105-J100 -> 10603.529 | ... N101: =N98+N105-N100 -> 10438.711 | O101: =O98+O99-O100 -> 18458.883 | P101: =P98+P99-P100 -> 17905.117 | Q101: =Q98+Q99-Q100 -> 17367.963 | R101: =R98+R99-R100 -> 25180.257 | S101: =S98+S99-S100 -> 24424.85 | T101: =T98+T99-T100 -> 23692.104 | U101: =U98+U99-U100 -> 31314.674 | V101: =V98+V99-V100 -> 30375.234 | ... BJ101: =BJ98+BJ99-BJ100 -> 51722.171
A103: Organic Adds Subscribers Cable
A104: Opening Subscribers | C104: 0 | D104: =C107 -> 275 | E104: =D107 -> 541.75 | F104: =E107 -> 800.4975 | G104: =F107 -> 1051.4826 | H104: =G107 -> 1294.9381 | I104: =H107 -> 1531.09 | J104: =I107 -> 1760.1573 | K104: =J107 -> 1982.3525 | ... BJ104: =BI107 -> 25699.691
A105: Additions | C105: =VLOOKUP(Assumptions!$G$10,Organic_Sub_Adds,'Financial Statements & Detail'!C5+1)/12 -> 275 | D105: =VLOOKUP(Assumptions!$G$10,Organic_Sub_Adds,'Financial Statements & Detail'!D5+1)/12 -> 275 | E105: =VLOOKUP(Assumptions!$G$10,Organic_Sub_Adds,'Financial Statements & Detail'!E5+1)/12 -> 275 | F105: =VLOOKUP(Assumptions!$G$10,Organic_Sub_Adds,'Financial Statements & Detail'!F5+1)/12 -> 275 | G105: =VLOOKUP(Assumptions!$G$10,Organic_Sub_Adds,'Financial Statements & Detail'!G5+1)/12 -> 275 | H105: =VLOOKUP(Assumptions!$G$10,Organic_Sub_Adds,'Financial Statements & Detail'!H5+1)/12 -> 275 | I105: =VLOOKUP(Assumptions!$G$10,Organic_Sub_Adds,'Financial Statements & Detail'!I5+1)/12 -> 275 | J105: =VLOOKUP(Assumptions!$G$10,Organic_Sub_Adds,'Financial Statements & Detail'!J5+1)/12 -> 275 | ... BJ105: =VLOOKUP(Assumptions!$G$10,Organic_Sub_Adds,'Financial Statements & Detail'!BJ5+1)/12 -> 1433.3333
A106: Attrition | C106: =Cable_Attrition*'Financial Statements & Detail'!C104 -> 0 | D106: =Cable_Attrition*'Financial Statements & Detail'!D104 -> 8.25 | E106: =Cable_Attrition*'Financial Statements & Detail'!E104 -> 16.2525 | F106: =Cable_Attrition*'Financial Statements & Detail'!F104 -> 24.014925 | G106: =Cable_Attrition*'Financial Statements & Detail'!G104 -> 31.544477 | H106: =Cable_Attrition*'Financial Statements & Detail'!H104 -> 38.848143 | I106: =Cable_Attrition*'Financial Statements & Detail'!I104 -> 45.932699 | J106: =Cable_Attrition*'Financial Statements & Detail'!J104 -> 52.804718 | ... BJ106: =Cable_Attrition*'Financial Statements & Detail'!BJ104 -> 770.99074
A107: Ending | C107: =C104+C105-C106 -> 275 | D107: =D104+D105-D106 -> 541.75 | E107: =E104+E105-E106 -> 800.4975 | F107: =F104+F105-F106 -> 1051.4826 | G107: =G104+G105-G106 -> 1294.9381 | H107: =H104+H105-H106 -> 1531.09 | I107: =I104+I105-I106 -> 1760.1573 | J107: =J104+J105-J106 -> 1982.3525 | ... BJ107: =BJ104+BJ105-BJ106 -> 26362.034
A109: Total Opening Subscribers-Cable | C109: =C98+C104 -> 11000 | D109: =D98+D104 -> 11220 | E109: =E98+E104 -> 11433.4 | F109: =F98+F104 -> 11640.398 | G109: =G98+G104 -> 11841.186 | H109: =H98+H104 -> 12035.95 | I109: =I98+I104 -> 12224.872 | J109: =J98+J104 -> 12408.126 | ... BJ109: =BJ98+BJ104 -> 79021.517
A111: Subscribers Other-Net of Attrition
A112: Voice | C112: =C109*with_Voice*(1-Attrition_Voice) -> 2681.25 | D112: =D109*with_Voice*(1-Attrition_Voice) -> 2734.875 | E112: =E109*with_Voice*(1-Attrition_Voice) -> 2786.8912 | F112: =F109*with_Voice*(1-Attrition_Voice) -> 2837.347 | G112: =G109*with_Voice*(1-Attrition_Voice) -> 2886.2891 | H112: =H109*with_Voice*(1-Attrition_Voice) -> 2933.7629 | I112: =I109*with_Voice*(1-Attrition_Voice) -> 2979.8125 | J112: =J109*with_Voice*(1-Attrition_Voice) -> 3024.4807 | ... BJ112: =BJ109*with_Voice*(1-Attrition_Voice) -> 19261.495
A113: Data | C113: =C109*with_Data*(1-Attrition_Data) -> 3811.5 | D113: =D109*with_Data*(1-Attrition_Data) -> 3887.73 | E113: =E109*with_Data*(1-Attrition_Data) -> 3961.6731 | F113: =F109*with_Data*(1-Attrition_Data) -> 4033.3979 | G113: =G109*with_Data*(1-Attrition_Data) -> 4102.971 | H113: =H109*with_Data*(1-Attrition_Data) -> 4170.4568 | I113: =I109*with_Data*(1-Attrition_Data) -> 4235.9181 | J113: =J109*with_Data*(1-Attrition_Data) -> 4299.4156 | ... BJ113: =BJ109*with_Data*(1-Attrition_Data) -> 27380.956
A114: Voice/Data | C114: =C109*with_Voice___Data*(1-Attrition_Voice) -> 2145 | D114: =D109*with_Voice___Data*(1-Attrition_Voice) -> 2187.9 | E114: =E109*with_Voice___Data*(1-Attrition_Voice) -> 2229.513 | F114: =F109*with_Voice___Data*(1-Attrition_Voice) -> 2269.8776 | G114: =G109*with_Voice___Data*(1-Attrition_Voice) -> 2309.0313 | H114: =H109*with_Voice___Data*(1-Attrition_Voice) -> 2347.0103 | I114: =I109*with_Voice___Data*(1-Attrition_Voice) -> 2383.85 | J114: =J109*with_Voice___Data*(1-Attrition_Voice) -> 2419.5845 | ... BJ114: =BJ109*with_Voice___Data*(1-Attrition_Voice) -> 15409.196
A115: Total Voice | C115: =C112+C114 -> 4826.25 | D115: =D112+D114 -> 4922.775 | E115: =E112+E114 -> 5016.4042 | F115: =F112+F114 -> 5107.2246 | G115: =G112+G114 -> 5195.3204 | H115: =H112+H114 -> 5280.7733 | I115: =I112+I114 -> 5363.6626 | J115: =J112+J114 -> 5444.0652 | ... BJ115: =BJ112+BJ114 -> 34670.691
A116: Total Data | C116: =C113+C114 -> 5956.5 | D116: =D113+D114 -> 6075.63 | E116: =E113+E114 -> 6191.1861 | F116: =F113+F114 -> 6303.2755 | G116: =G113+G114 -> 6412.0023 | H116: =H113+H114 -> 6517.4672 | I116: =I113+I114 -> 6619.7682 | J116: =J113+J114 -> 6719.0001 | ... BJ116: =BJ113+BJ114 -> 42790.151
A118: Revenue Subscription Fee
A119: Cable | C119: =C109*ARPU_Cable -> 159500 | D119: =D109*ARPU_Cable -> 162690 | E119: =E109*ARPU_Cable -> 165784.3 | F119: =F109*ARPU_Cable -> 168785.77 | G119: =G109*ARPU_Cable -> 171697.2 | H119: =H109*ARPU_Cable -> 174521.28 | I119: =I109*ARPU_Cable -> 177260.64 | J119: =J109*ARPU_Cable -> 179917.82 | ... BJ119: =BJ109*ARPU_Cable -> 1145812
A120: Voice | C120: =C112*ARPU_Voice -> 53625 | D120: =D112*ARPU_Voice -> 54697.5 | E120: =E112*ARPU_Voice -> 55737.825 | F120: =F112*ARPU_Voice -> 56746.94 | G120: =G112*ARPU_Voice -> 57725.782 | H120: =H112*ARPU_Voice -> 58675.259 | I120: =I112*ARPU_Voice -> 59596.251 | J120: =J112*ARPU_Voice -> 60489.613 | ... BJ120: =BJ112*ARPU_Voice -> 385229.89
...

Sheet Cashflow
A2: Cash Flow Statement
A3: US$
C6: 39455 | D6: 39486 | E6: 39515 | F6: 39546 | G6: 39576 | H6: 39607 | I6: 39637 | J6: 39668 | K6: 39699 | L6: 39729 | M6: 39760 | N6: 39790 | O6: 39821 | P6: 39852 | Q6: 39880 | R6: 39911 | S6: 39941 | T6: 39972 | U6: 40002 | V6: 40033 | W6: 40064 | X6: 40094 | Y6: 40125 | Z6: 40155 | AA6: 40186 | AB6: 40217 | AC6: 40245 | AD6: 40276 | AE6: 40306 | AF6: 40337 | AG6: 40367 | AH6: 40398 | AI6: 40429 | AJ6: 40459 | AK6: 40490 | AL6: 40520 | AM6: 40551 | AN6: 40582 | AO6: 40610 | AP6: 40641 | AQ6: 40671 | AR6: 40702 | AS6: 40732 | AT6: 40763 | AU6: 40794 | AV6: 40824 | AW6: 40855 | AX6: 40885 | AY6: 40916 | AZ6: 40947 | BA6: 40976 | BB6: 41007 | BC6: 41037 | BD6: 41068 | BE6: 41098 | BF6: 41129 | BG6: 41160 | BH6: 41190 | BI6: 41221 | BJ6: 41251
A8: Cash provided by (used in)
A10: Operating activities
A11: Net income (loss) for the period | C11: ='Financial Statements & Detail'!C83 -> -102573.25 | D11: ='Financial Statements & Detail'!D83 -> -23581.395 | E11: ='Financial Statements & Detail'!E83 -> -26663.564 | F11: ='Financial Statements & Detail'!F83 -> -24163.246 | G11: ='Financial Statements & Detail'!G83 -> -21501.54 | H11: ='Financial Statements & Detail'!H83 -> -20169.663 | I11: ='Financial Statements & Detail'!I83 -> -18036.445 | J11: ='Financial Statements & Detail'!J83 -> -15730.826 | ... BJ11: ='Financial Statements & Detail'!BJ83 -> 549153.77
A12: Non-cash transactions
A13: Depreciation | C13: ='Financial Statements & Detail'!C244 -> 80169.301 | D13: ='Financial Statements & Detail'!D244 -> 81852.77 | E13: ='Financial Statements & Detail'!E244 -> 83358.051 | F13: ='Financial Statements & Detail'!F244 -> 84852.155 | G13: ='Financial Statements & Detail'!G244 -> 86335.419 | H13: ='Financial Statements & Detail'!H244 -> 87808.166 | I13: ='Financial Statements & Detail'!I244 -> 89270.714 | J13: ='Financial Statements & Detail'!J244 -> 90723.367 | ... BJ13: ='Financial Statements & Detail'!BJ244 -> 815012.99
A14: Amortization | C14: 0 | D14: 0 | E14: 0 | F14: 0 | G14: 0 | H14: 0 | I14: 0 | J14: 0 | K14: 0 | L14: 0 | M14: 0 | N14: 0 | O14: 0 | P14: 0 | Q14: 0 | R14: 0 | S14: 0 | T14: 0 | U14: 0 | V14: 0 | W14: 0 | X14: 0 | Y14: 0 | Z14: 0 | AA14: 0 | AB14: 0 | AC14: 0 | AD14: 0 | AE14: 0 | AF14: 0 | AG14: 0 | AH14: 0 | AI14: 0 | AJ14: 0 | AK14: 0 | AL14: 0 | AM14: 0 | AN14: 0 | AO14: 0 | AP14: 0 | AQ14: 0 | AR14: 0 | AS14: 0 | AT14: 0 | AU14: 0 | AV14: 0 | AW14: 0 | AX14: 0 | AY14: 0 | AZ14: 0 | BA14: 0 | BB14: 0 | BC14: 0 | BD14: 0 | BE14: 0 | BF14: 0 | BG14: 0 | BH14: 0 | BI14: 0 | BJ14: 0
A15: Non-cash interest accrued | C15: 0 | D15: 0 | E15: 0 | F15: 0 | G15: 0 | H15: 0 | I15: 0 | J15: 0 | K15: 0 | L15: 0 | M15: 0 | N15: 0 | O15: 0 | P15: 0 | Q15: 0 | R15: 0 | S15: 0 | T15: 0 | U15: 0 | V15: 0 | W15: 0 | X15: 0 | Y15: 0 | Z15: 0 | AA15: 0 | AB15: 0 | AC15: 0 | AD15: 0 | AE15: 0 | AF15: 0 | AG15: 0 | AH15: 0 | AI15: 0 | AJ15: 0 | AK15: 0 | AL15: 0 | AM15: 0 | AN15: 0 | AO15: 0 | AP15: 0 | AQ15: 0 | AR15: 0 | AS15: 0 | AT15: 0 | AU15: 0 | AV15: 0 | AW15: 0 | AX15: 0 | AY15: 0 | AZ15: 0 | BA15: 0 | BB15: 0 | BC15: 0 | BD15: 0 | BE15: 0 | BF15: 0 | BG15: 0 | BH15: 0 | BI15: 0 | BJ15: 0
A16: Sub-total | C16: =SUM(C13:C15) -> 80169.301 | D16: =SUM(D13:D15) -> 81852.77 | E16: =SUM(E13:E15) -> 83358.051 | F16: =SUM(F13:F15) -> 84852.155 | G16: =SUM(G13:G15) -> 86335.419 | H16: =SUM(H13:H15) -> 87808.166 | I16: =SUM(I13:I15) -> 89270.714 | J16: =SUM(J13:J15) -> 90723.367 | ... BJ16: =SUM(BJ13:BJ15) -> 815012.99
A17: Changes in assets and liabilities
A18: Accounts receivable | C18: ='Financial Statements & Detail'!B47-'Financial Statements & Detail'!C47 -> -755433.94 | D18: ='Financial Statements & Detail'!C47-'Financial Statements & Detail'!D47 -> -15108.679 | E18: ='Financial Statements & Detail'!D47-'Financial Statements & Detail'!E47 -> -14655.418 | F18: ='Financial Statements & Detail'!E47-'Financial Statements & Detail'!F47 -> -14215.756 | G18: ='Financial Statements & Detail'!F47-'Financial Statements & Detail'!G47 -> -13789.283 | H18: ='Financial Statements & Detail'!G47-'Financial Statements & Detail'!H47 -> -13375.605 | I18: ='Financial Statements & Detail'!H47-'Financial Statements & Detail'!I47 -> -12974.337 | J18: ='Financial Statements & Detail'!I47-'Financial Statements & Detail'!J47 -> -12585.106 | ... BJ18: ='Financial Statements & Detail'!BI47-'Financial Statements & Detail'!BJ47 -> 66429.796
A19: Inventories | C19: ='Financial Statements & Detail'!B48-'Financial Statements & Detail'!C48 -> -191924.09 | D19: ='Financial Statements & Detail'!C48-'Financial Statements & Detail'!D48 -> 432.72281 | E19: ='Financial Statements & Detail'!D48-'Financial Statements & Detail'!E48 -> 419.74113 | F19: ='Financial Statements & Detail'!E48-'Financial Statements & Detail'!F48 -> 407.14889 | G19: ='Financial Statements & Detail'!F48-'Financial Statements & Detail'!G48 -> 394.93443 | H19: ='Financial Statements & Detail'!G48-'Financial Statements & Detail'!H48 -> 383.08639 | I19: ='Financial Statements & Detail'!H48-'Financial Statements & Detail'!I48 -> 371.5938 | J19: ='Financial Statements & Detail'!I48-'Financial Statements & Detail'!J48 -> 360.44599 | ... BJ19: ='Financial Statements & Detail'!BI48-'Financial Statements & Detail'!BJ48 -> 0
A20: Prepaid expenses | C20: ='Financial Statements & Detail'!B49-'Financial Statements & Detail'!C49 -> 0 | D20: ='Financial Statements & Detail'!C49-'Financial Statements & Detail'!D49 -> 0 | E20: ='Financial Statements & Detail'!D49-'Financial Statements & Detail'!E49 -> 0 | F20: ='Financial Statements & Detail'!E49-'Financial Statements & Detail'!F49 -> 0 | G20: ='Financial Statements & Detail'!F49-'Financial Statements & Detail'!G49 -> 0 | H20: ='Financial Statements & Detail'!G49-'Financial Statements & Detail'!H49 -> 0 | I20: ='Financial Statements & Detail'!H49-'Financial Statements & Detail'!I49 -> 0 | J20: ='Financial Statements & Detail'!I49-'Financial Statements & Detail'!J49 -> 0 | ... BJ20: ='Financial Statements & Detail'!BI49-'Financial Statements & Detail'!BJ49 -> 0
A21: Other Assets | C21: ='Financial Statements & Detail'!B58-'Financial Statements & Detail'!C58 -> -6500000 | D21: ='Financial Statements & Detail'!C58-'Financial Statements & Detail'!D58 -> 0 | E21: ='Financial Statements & Detail'!D58-'Financial Statements & Detail'!E58 -> 0 | F21: ='Financial Statements & Detail'!E58-'Financial Statements & Detail'!F58 -> 0 | G21: ='Financial Statements & Detail'!F58-'Financial Statements & Detail'!G58 -> 0 | H21: ='Financial Statements & Detail'!G58-'Financial Statements & Detail'!H58 -> 0 | I21: ='Financial Statements & Detail'!H58-'Financial Statements & Detail'!I58 -> 0 | J21: ='Financial Statements & Detail'!I58-'Financial Statements & Detail'!J58 -> 0 | ... BJ21: ='Financial Statements & Detail'!BI58-'Financial Statements & Detail'!BJ58 -> 0
A22: Accounts payable | C22: ='Financial Statements & Detail'!C66-'Financial Statements & Detail'!B66 -> 41924.094 | D22: ='Financial Statements & Detail'!D66-'Financial Statements & Detail'!C66 -> -432.72281 | E22: ='Financial Statements & Detail'!E66-'Financial Statements & Detail'!D66 -> -419.74113 | F22: ='Financial Statements & Detail'!F66-'Financial Statements & Detail'!E66 -> -407.14889 | G22: ='Financial Statements & Detail'!G66-'Financial Statements & Detail'!F66 -> -394.93443 | H22: ='Financial Statements & Detail'!H66-'Financial Statements & Detail'!G66 -> -383.08639 | I22: ='Financial Statements & Detail'!I66-'Financial Statements & Detail'!H66 -> -371.5938 | J22: ='Financial Statements & Detail'!J66-'Financial Statements & Detail'!I66 -> -360.44599 | ... BJ22: ='Financial Statements & Detail'!BJ66-'Financial Statements & Detail'!BI66 -> 0
A23: Accrued expenses | C23: ='Financial Statements & Detail'!C67-'Financial Statements & Detail'!B67 -> 107420.62 | D23: ='Financial Statements & Detail'!D67-'Financial Statements & Detail'!C67 -> -38098.3 | E23: ='Financial Statements & Detail'!E67-'Financial Statements & Detail'!D67 -> -23.4135 | F23: ='Financial Statements & Detail'!F67-'Financial Statements & Detail'!E67 -> 121.03891 | G23: ='Financial Statements & Detail'!G67-'Financial Statements & Detail'!F67 -> -22.029762 | H23: ='Financial Statements & Detail'!H67-'Financial Statements & Detail'!G67 -> 582.38113 | I23: ='Financial Statements & Detail'!I67-'Financial Statements & Detail'!H67 -> 123.0222 | J23: ='Financial Statements & Detail'!J67-'Financial Statements & Detail'!I67 -> -20.105969 | ... BJ23: ='Financial Statements & Detail'!BJ67-'Financial Statements & Detail'!BI67 -> -287.5
A24: Income taxes payable | C24: ='Financial Statements & Detail'!C68-'Financial Statements & Detail'!B68 -> 0 | D24: ='Financial Statements & Detail'!D68-'Financial Statements & Detail'!C68 -> 0 | E24: ='Financial Statements & Detail'!E68-'Financial Statements & Detail'!D68 -> 0 | F24: ='Financial Statements & Detail'!F68-'Financial Statements & Detail'!E68 -> 0 | G24: ='Financial Statements & Detail'!G68-'Financial Statements & Detail'!F68 -> 0 | H24: ='Financial Statements & Detail'!H68-'Financial Statements & Detail'!G68 -> 0 | I24: ='Financial Statements & Detail'!I68-'Financial Statements & Detail'!H68 -> 0 | J24: ='Financial Statements & Detail'!J68-'Financial Statements & Detail'!I68 -> 0 | ... BJ24: ='Financial Statements & Detail'!BJ68-'Financial Statements & Detail'!BI68 -> -9366.0789
A25: Sub-total | C25: =SUM(C18:C24) -> -7298013.3 | D25: =SUM(D18:D24) -> -53206.979 | E25: =SUM(E18:E24) -> -14678.832 | F25: =SUM(F18:F24) -> -14094.717 | G25: =SUM(G18:G24) -> -13811.313 | H25: =SUM(H18:H24) -> -12793.224 | I25: =SUM(I18:I24) -> -12851.314 | J25: =SUM(J18:J24) -> -12605.212 | ... BJ25: =SUM(BJ18:BJ24) -> 56776.217
A26: Total Operating Activities | C26: =C11+C16+C25 -> -7320417.3 | D26: =D11+D16+D25 -> 5064.3962 | E26: =E11+E16+E25 -> 42015.655 | F26: =F11+F16+F25 -> 46594.192 | G26: =G11+G16+G25 -> 51022.566 | H26: =H11+H16+H25 -> 54845.28 | I26: =I11+I16+I25 -> 58382.955 | J26: =J11+J16+J25 -> 62387.329 | ... BJ26: =BJ11+BJ16+BJ25 -> 1420943 | BK26: =SUM(AY26:BJ26) -> 6281825.3
A28: Investing Activities
A29: Purchase of PPE | C29: ='Financial Statements & Detail'!B54-'Financial Statements & Detail'!C54 -> -4810158 | D29: ='Financial Statements & Detail'!C54-'Financial Statements & Detail'!D54 -> -101008.16 | E29: ='Financial Statements & Detail'!D54-'Financial Statements & Detail'!E54 -> -90316.844 | F29: ='Financial Statements & Detail'!E54-'Financial Statements & Detail'!F54 -> -89646.268 | G29: ='Financial Statements & Detail'!F54-'Financial Statements & Detail'!G54 -> -88995.808 | H29: ='Financial Statements & Detail'!G54-'Financial Statements & Detail'!H54 -> -88364.863 | I29: ='Financial Statements & Detail'!H54-'Financial Statements & Detail'!I54 -> -87752.845 | J29: ='Financial Statements & Detail'!I54-'Financial Statements & Detail'!J54 -> -87159.188 | ... BJ29: ='Financial Statements & Detail'!BI54-'Financial Statements & Detail'!BJ54 -> -344238.1
A30: Leasehold improvements | C30: 0 | D30: 0 | E30: 0 | F30: 0 | G30: 0 | H30: 0 | I30: 0 | J30: 0 | K30: 0 | L30: 0 | M30: 0 | N30: 0 | O30: 0 | P30: 0 | Q30: 0 | R30: 0 | S30: 0 | T30: 0 | U30: 0 | V30: 0 | W30: 0 | X30: 0 | Y30: 0 | Z30: 0 | AA30: 0 | AB30: 0 | AC30: 0 | AD30: 0 | AE30: 0 | AF30: 0 | AG30: 0 | AH30: 0 | AI30: 0 | AJ30: 0 | AK30: 0 | AL30: 0 | AM30: 0 | AN30: 0 | AO30: 0 | AP30: 0 | AQ30: 0 | AR30: 0 | AS30: 0 | AT30: 0 | AU30: 0 | AV30: 0 | AW30: 0 | AX30: 0 | AY30: 0 | AZ30: 0 | BA30: 0 | BB30: 0 | BC30: 0 | BD30: 0 | BE30: 0 | BF30: 0 | BG30: 0 | BH30: 0 | BI30: 0 | BJ30: 0
A31: Total | C31: =SUM(C29:C30) -> -4810158 | D31: =SUM(D29:D30) -> -101008.16 | E31: =SUM(E29:E30) -> -90316.844 | F31: =SUM(F29:F30) -> -89646.268 | G31: =SUM(G29:G30) -> -88995.808 | H31: =SUM(H29:H30) -> -88364.863 | I31: =SUM(I29:I30) -> -87752.845 | J31: =SUM(J29:J30) -> -87159.188 | ... BJ31: =SUM(BJ29:BJ30) -> -344238.1 | BK31: =SUM(AY31:BJ31) -> -11177877
A32: Financing activities
A33: Line of credit | C33: ='Financial Statements & Detail'!C64-'Financial Statements & Detail'!B64 -> 0 | D33: ='Financial Statements & Detail'!D64-'Financial Statements & Detail'!C64 -> 0 | E33: ='Financial Statements & Detail'!E64-'Financial Statements & Detail'!D64 -> 0 | F33: ='Financial Statements & Detail'!F64-'Financial Statements & Detail'!E64 -> 0 | G33: ='Financial Statements & Detail'!G64-'Financial Statements & Detail'!F64 -> 0 | H33: ='Financial Statements & Detail'!H64-'Financial Statements & Detail'!G64 -> 0 | I33: ='Financial Statements & Detail'!I64-'Financial Statements & Detail'!H64 -> 0 | J33: ='Financial Statements & Detail'!J64-'Financial Statements & Detail'!I64 -> 0 | ... BJ33: ='Financial Statements & Detail'!BJ64-'Financial Statements & Detail'!BI64 -> 0
A34: Long Term Debt | C34: ='Financial Statements & Detail'!C65+'Financial Statements & Detail'!C72-'Financial Statements & Detail'!B65-'Financial Statements & Detail'!B72 -> 0 | D34: ='Financial Statements & Detail'!D65+'Financial Statements & Detail'!D72-'Financial Statements & Detail'!C65-'Financial Statements & Detail'!C72 -> 0 | E34: ='Financial Statements & Detail'!E65+'Financial Statements & Detail'!E72-'Financial Statements & Detail'!D65-'Financial Statements & Detail'!D72 -> 0 | F34: ='Financial Statements & Detail'!F65+'Financial Statements & Detail'!F72-'Financial Statements & Detail'!E65-'Financial Statements & Detail'!E72 -> 0 | G34: ='Financial Statements & Detail'!G65+'Financial Statements & Detail'!G72-'Financial Statements & Detail'!F65-'Financial Statements & Detail'!F72 -> 0 | H34: ='Financial Statements & Detail'!H65+'Financial Statements & Detail'!H72-'Financial Statements & Detail'!G65-'Financial Statements & Detail'!G72 -> 0 | I34: ='Financial Statements & Detail'!I65+'Financial Statements & Detail'!I72-'Financial Statements & Detail'!H65-'Financial Statements & Detail'!H72 -> 0 | J34: ='Financial Statements & Detail'!J65+'Financial Statements & Detail'!J72-'Financial Statements & Detail'!I65-'Financial Statements & Detail'!I72 -> 0 | ... BJ34: ='Financial Statements & Detail'!BJ65+'Financial Statements & Detail'!BJ72-'Financial Statements & Detail'!BI65-'Financial Statements & Detail'!BI72 -> -431984.23
A35: Proceeds from stock | C35: ='Financial Statements & Detail'!C78-'Financial Statements & Detail'!B78 -> 15310158 | D35: ='Financial Statements & Detail'!D78-'Financial Statements & Detail'!C78 -> 0 | E35: ='Financial Statements & Detail'!E78-'Financial Statements & Detail'!D78 -> 0 | F35: ='Financial Statements & Detail'!F78-'Financial Statements & Detail'!E78 -> 0 | G35: ='Financial Statements & Detail'!G78-'Financial Statements & Detail'!F78 -> 0 | H35: ='Financial Statements & Detail'!H78-'Financial Statements & Detail'!G78 -> 0 | I35: ='Financial Statements & Detail'!I78-'Financial Statements & Detail'!H78 -> 0 | J35: ='Financial Statements & Detail'!J78-'Financial Statements & Detail'!I78 -> 0 | ... BJ35: ='Financial Statements & Detail'!BJ78-'Financial Statements & Detail'!BI78 -> 0
A36: Due to shareholders | C36: ='Financial Statements & Detail'!C73-'Financial Statements & Detail'!B73 -> 0 | D36: ='Financial Statements & Detail'!D73-'Financial Statements & Detail'!C73 -> 0 | E36: ='Financial Statements & Detail'!E73-'Financial Statements & Detail'!D73 -> 0 | F36: ='Financial Statements & Detail'!F73-'Financial Statements & Detail'!E73 -> 0 | G36: ='Financial Statements & Detail'!G73-'Financial Statements & Detail'!F73 -> 0 | H36: ='Financial Statements & Detail'!H73-'Financial Statements & Detail'!G73 -> 0 | I36: ='Financial Statements & Detail'!I73-'Financial Statements & Detail'!H73 -> 0 | J36: ='Financial Statements & Detail'!J73-'Financial Statements & Detail'!I73 -> 0 | ... BJ36: ='Financial Statements & Detail'!BJ73-'Financial Statements & Detail'!BI73 -> 0
A37: Total | C37: =SUM(C33:C36) -> 15310158 | D37: =SUM(D33:D36) -> 0 | E37: =SUM(E33:E36) -> 0 | F37: =SUM(F33:F36) -> 0 | G37: =SUM(G33:G36) -> 0 | H37: =SUM(H33:H36) -> 0 | I37: =SUM(I33:I36) -> 0 | J37: =SUM(J33:J36) -> 0 | ... BJ37: =SUM(BJ33:BJ36) -> -431984.23
A39: Increase (decrease) in cash during period | C39: =C26+C31+C37 -> 3179582.7 | D39: =D26+D31+D37 -> -95943.765 | E39: =E26+E31+E37 -> -48301.19 | F39: =F26+F31+F37 -> -43052.075 | G39: =G26+G31+G37 -> -37973.243 | H39: =H26+H31+H37 -> -33519.583 | I39: =I26+I31+I37 -> -29369.891 | J39: =J26+J31+J37 -> -24771.86 | ... BJ39: =BJ26+BJ31+BJ37 -> 644720.65
A40: Cash beginning of period | C40: 0 | D40: =C41 -> 3179582.7 | E40: =D41 -> 3083639 | F40: =E41 -> 3035337.8 | G40: =F41 -> 2992285.7 | H40: =G41 -> 2954312.5 | I40: =H41 -> 2920792.9 | J40: =I41 -> 2891423 | K40: =J41 -> 2866651.1 | ... BJ40: =BI41 -> 4363246.3
A41: Cash end of period | C41: =SUM(C39:C40) -> 3179582.7 | D41: =SUM(D39:D40) -> 3083639 | E41: =SUM(E39:E40) -> 3035337.8 | F41: =SUM(F39:F40) -> 2992285.7 | G41: =SUM(G39:G40) -> 2954312.5 | H41: =SUM(H39:H40) -> 2920792.9 | I41: =SUM(I39:I40) -> 2891423 | J41: =SUM(J39:J40) -> 2866651.1 | ... BJ41: =SUM(BJ39:BJ40) -> 5007966.9

Sheet OPEX
A2: OPEX
A3: US$
C6: 39455 | D6: 39486 | E6: 39515 | F6: 39546 | G6: 39576 | H6: 39607 | I6: 39637 | J6: 39668 | K6: 39699 | L6: 39729 | M6: 39760 | N6: 39790 | O6: 39821 | P6: 39852 | Q6: 39880 | R6: 39911 | S6: 39941 | T6: 39972 | U6: 40002 | V6: 40033 | W6: 40064 | X6: 40094 | Y6: 40125 | Z6: 40155 | AA6: 40186 | AB6: 40217 | AC6: 40245 | AD6: 40276 | AE6: 40306 | AF6: 40337 | AG6: 40367 | AH6: 40398 | AI6: 40429 | AJ6: 40459 | AK6: 40490 | AL6: 40520 | AM6: 40551 | AN6: 40582 | AO6: 40610 | AP6: 40641 | AQ6: 40671 | AR6: 40702 | AS6: 40732 | AT6: 40763 | AU6: 40794 | AV6: 40824 | AW6: 40855 | AX6: 40885 | AY6: 40916 | AZ6: 40947 | BA6: 40976 | BB6: 41007 | BC6: 41037 | BD6: 41068 | BE6: 41098 | BF6: 41129 | BG6: 41160 | BH6: 41190 | BI6: 41221 | BJ6: 41251
A11: Operating Expenses
A12: Advertising & Promotion | C12: =C99 -> 79420 | D12: =D99 -> 2935.9 | E12: =E99 -> 2889.073 | F12: =F99 -> 2843.6508 | G12: =G99 -> 2799.5913 | H12: =H99 -> 2756.8535 | I12: =I99 -> 2715.3979 | J12: =J99 -> 2675.186 | ... BJ12: =BJ99 -> 7166.6667
A13: Auto | C13: 0 | D13: 0 | E13: 0 | F13: 0 | G13: 0 | H13: 0 | I13: 0 | J13: 0 | K13: 0 | L13: 0 | M13: 0 | N13: 0 | O13: 0 | P13: 0 | Q13: 0 | R13: 0 | S13: 0 | T13: 0 | U13: 0 | V13: 0 | W13: 0 | X13: 0 | Y13: 0 | Z13: 0 | AA13: 0 | AB13: 0 | AC13: 0 | AD13: 0 | AE13: 0 | AF13: 0 | AG13: 0 | AH13: 0 | AI13: 0 | AJ13: 0 | AK13: 0 | AL13: 0 | AM13: 0 | AN13: 0 | AO13: 0 | AP13: 0 | AQ13: 0 | AR13: 0 | AS13: 0 | AT13: 0 | AU13: 0 | AV13: 0 | AW13: 0 | AX13: 0 | AY13: 0 | AZ13: 0 | BA13: 0 | BB13: 0 | BC13: 0 | BD13: 0 | BE13: 0 | BF13: 0 | BG13: 0 | BH13: 0 | BI13: 0 | BJ13: 0
A14: Bad Debts | C14: 0 | D14: 0 | E14: 0 | F14: 0 | G14: 0 | H14: 0 | I14: 0 | J14: 0 | K14: 0 | L14: 0 | M14: 0 | N14: 0 | O14: 0 | P14: 0 | Q14: 0 | R14: 0 | S14: 0 | T14: 0 | U14: 0 | V14: 0 | W14: 0 | X14: 0 | Y14: 0 | Z14: 0 | AA14: 0 | AB14: 0 | AC14: 0 | AD14: 0 | AE14: 0 | AF14: 0 | AG14: 0 | AH14: 0 | AI14: 0 | AJ14: 0 | AK14: 0 | AL14: 0 | AM14: 0 | AN14: 0 | AO14: 0 | AP14: 0 | AQ14: 0 | AR14: 0 | AS14: 0 | AT14: 0 | AU14: 0 | AV14: 0 | AW14: 0 | AX14: 0 | AY14: 0 | AZ14: 0 | BA14: 0 | BB14: 0 | BC14: 0 | BD14: 0 | BE14: 0 | BF14: 0 | BG14: 0 | BH14: 0 | BI14: 0 | BJ14: 0
A15: Bank Service Charges | C15: 0 | D15: 0 | E15: 0 | F15: 0 | G15: 0 | H15: 0 | I15: 0 | J15: 0 | K15: 0 | L15: 0 | M15: 0 | N15: 0 | O15: 0 | P15: 0 | Q15: 0 | R15: 0 | S15: 0 | T15: 0 | U15: 0 | V15: 0 | W15: 0 | X15: 0 | Y15: 0 | Z15: 0 | AA15: 0 | AB15: 0 | AC15: 0 | AD15: 0 | AE15: 0 | AF15: 0 | AG15: 0 | AH15: 0 | AI15: 0 | AJ15: 0 | AK15: 0 | AL15: 0 | AM15: 0 | AN15: 0 | AO15: 0 | AP15: 0 | AQ15: 0 | AR15: 0 | AS15: 0 | AT15: 0 | AU15: 0 | AV15: 0 | AW15: 0 | AX15: 0 | AY15: 0 | AZ15: 0 | BA15: 0 | BB15: 0 | BC15: 0 | BD15: 0 | BE15: 0 | BF15: 0 | BG15: 0 | BH15: 0 | BI15: 0 | BJ15: 0
A16: Consultants | C16: 0 | D16: 0 | E16: 0 | F16: 0 | G16: 0 | H16: 0 | I16: 0 | J16: 0 | K16: 0 | L16: 0 | M16: 0 | N16: 0 | O16: 0 | P16: 0 | Q16: 0 | R16: 0 | S16: 0 | T16: 0 | U16: 0 | V16: 0 | W16: 0 | X16: 0 | Y16: 0 | Z16: 0 | AA16: 0 | AB16: 0 | AC16: 0 | AD16: 0 | AE16: 0 | AF16: 0 | AG16: 0 | AH16: 0 | AI16: 0 | AJ16: 0 | AK16: 0 | AL16: 0 | AM16: 0 | AN16: 0 | AO16: 0 | AP16: 0 | AQ16: 0 | AR16: 0 | AS16: 0 | AT16: 0 | AU16: 0 | AV16: 0 | AW16: 0 | AX16: 0 | AY16: 0 | AZ16: 0 | BA16: 0 | BB16: 0 | BC16: 0 | BD16: 0 | BE16: 0 | BF16: 0 | BG16: 0 | BH16: 0 | BI16: 0 | BJ16: 0
A17: Employee Benefits | C17: =C79 -> 13946.25 | D17: =D79 -> 13983.75 | E17: =E79 -> 13983.75 | F17: =F79 -> 14021.25 | G17: =G79 -> 14021.25 | H17: =H79 -> 14178.75 | I17: =I79 -> 14216.25 | J17: =J79 -> 14216.25 | ... BJ17: =BJ79 -> 24448.75
A18: Equipment Leases | C18: 0 | D18: 0 | E18: 0 | F18: 0 | G18: 0 | H18: 0 | I18: 0 | J18: 0 | K18: 0 | L18: 0 | M18: 0 | N18: 0 | O18: 0 | P18: 0 | Q18: 0 | R18: 0 | S18: 0 | T18: 0 | U18: 0 | V18: 0 | W18: 0 | X18: 0 | Y18: 0 | Z18: 0 | AA18: 0 | AB18: 0 | AC18: 0 | AD18: 0 | AE18: 0 | AF18: 0 | AG18: 0 | AH18: 0 | AI18: 0 | AJ18: 0 | AK18: 0 | AL18: 0 | AM18: 0 | AN18: 0 | AO18: 0 | AP18: 0 | AQ18: 0 | AR18: 0 | AS18: 0 | AT18: 0 | AU18: 0 | AV18: 0 | AW18: 0 | AX18: 0 | AY18: 0 | AZ18: 0 | BA18: 0 | BB18: 0 | BC18: 0 | BD18: 0 | BE18: 0 | BF18: 0 | BG18: 0 | BH18: 0 | BI18: 0 | BJ18: 0
A19: Insurance | C19: =C103 -> 0 | D19: =D103 -> 0 | E19: =E103 -> 0 | F19: =F103 -> 0 | G19: =G103 -> 0 | H19: =H103 -> 0 | I19: =I103 -> 0 | J19: =J103 -> 0 | ... BJ19: =BJ103 -> 0
A20: Legal | C20: 0 | D20: 0 | E20: 0 | F20: 0 | G20: 0 | H20: 0 | I20: 0 | J20: 0 | K20: 0 | L20: 0 | M20: 0 | N20: 0 | O20: 0 | P20: 0 | Q20: 0 | R20: 0 | S20: 0 | T20: 0 | U20: 0 | V20: 0 | W20: 0 | X20: 0 | Y20: 0 | Z20: 0 | AA20: 0 | AB20: 0 | AC20: 0 | AD20: 0 | AE20: 0 | AF20: 0 | AG20: 0 | AH20: 0 | AI20: 0 | AJ20: 0 | AK20: 0 | AL20: 0 | AM20: 0 | AN20: 0 | AO20: 0 | AP20: 0 | AQ20: 0 | AR20: 0 | AS20: 0 | AT20: 0 | AU20: 0 | AV20: 0 | AW20: 0 | AX20: 0 | AY20: 0 | AZ20: 0 | BA20: 0 | BB20: 0 | BC20: 0 | BD20: 0 | BE20: 0 | BF20: 0 | BG20: 0 | BH20: 0 | BI20: 0 | BJ20: 0
A21: Office Rent | C21: =C104 -> 10000 | D21: =D104 -> 10000 | E21: =E104 -> 10000 | F21: =F104 -> 10000 | G21: =G104 -> 10000 | H21: =H104 -> 10000 | I21: =I104 -> 10000 | J21: =J104 -> 10000 | ... BJ21: =BJ104 -> 80000
A22: Office Supplies | C22: =C105 -> 1500 | D22: =D105 -> 1500 | E22: =E105 -> 1500 | F22: =F105 -> 1500 | G22: =G105 -> 1500 | H22: =H105 -> 1500 | I22: =I105 -> 1500 | J22: =J105 -> 1500 | ... BJ22: =BJ105 -> 24000
A23: Professional Fees | C23: =C101 -> 2000 | D23: =D101 -> 2000 | E23: =E101 -> 2000 | F23: =F101 -> 2000 | G23: =G101 -> 2000 | H23: =H101 -> 2000 | I23: =I101 -> 2000 | J23: =J101 -> 2000 | ... BJ23: =BJ101 -> 6000
A24: Salaries | C24: =C77 -> 92975 | D24: =D77 -> 93225 | E24: =E77 -> 93225 | F24: =F77 -> 93475 | G24: =G77 -> 93475 | H24: =H77 -> 94525 | I24: =I77 -> 94775 | J24: =J77 -> 94775 | ... BJ24: =BJ77 -> 162991.67
A25: Subscription/Membership | C25: 0 | D25: 0 | E25: 0 | F25: 0 | G25: 0 | H25: 0 | I25: 0 | J25: 0 | K25: 0 | L25: 0 | M25: 0 | N25: 0 | O25: 0 | P25: 0 | Q25: 0 | R25: 0 | S25: 0 | T25: 0 | U25: 0 | V25: 0 | W25: 0 | X25: 0 | Y25: 0 | Z25: 0 | AA25: 0 | AB25: 0 | AC25: 0 | AD25: 0 | AE25: 0 | AF25: 0 | AG25: 0 | AH25: 0 | AI25: 0 | AJ25: 0 | AK25: 0 | AL25: 0 | AM25: 0 | AN25: 0 | AO25: 0 | AP25: 0 | AQ25: 0 | AR25: 0 | AS25: 0 | AT25: 0 | AU25: 0 | AV25: 0 | AW25: 0 | AX25: 0 | AY25: 0 | AZ25: 0 | BA25: 0 | BB25: 0 | BC25: 0 | BD25: 0 | BE25: 0 | BF25: 0 | BG25: 0 | BH25: 0 | BI25: 0 | BJ25: 0
A26: Telephone | C26: 0 | D26: 0 | E26: 0 | F26: 0 | G26: 0 | H26: 0 | I26: 0 | J26: 0 | K26: 0 | L26: 0 | M26: 0 | N26: 0 | O26: 0 | P26: 0 | Q26: 0 | R26: 0 | S26: 0 | T26: 0 | U26: 0 | V26: 0 | W26: 0 | X26: 0 | Y26: 0 | Z26: 0 | AA26: 0 | AB26: 0 | AC26: 0 | AD26: 0 | AE26: 0 | AF26: 0 | AG26: 0 | AH26: 0 | AI26: 0 | AJ26: 0 | AK26: 0 | AL26: 0 | AM26: 0 | AN26: 0 | AO26: 0 | AP26: 0 | AQ26: 0 | AR26: 0 | AS26: 0 | AT26: 0 | AU26: 0 | AV26: 0 | AW26: 0 | AX26: 0 | AY26: 0 | AZ26: 0 | BA26: 0 | BB26: 0 | BC26: 0 | BD26: 0 | BE26: 0 | BF26: 0 | BG26: 0 | BH26: 0 | BI26: 0 | BJ26: 0
A27: Travel & Entertainmnet | C27: =C102 -> 5000 | D27: =D102 -> 5000 | E27: =E102 -> 5000 | F27: =F102 -> 5000 | G27: =G102 -> 5000 | H27: =H102 -> 5000 | I27: =I102 -> 5000 | J27: =J102 -> 5000 | ... BJ27: =BJ102 -> 25312.5
A28: Other | C28: 10000 | D28: 10000 | E28: 10000 | F28: 10000 | G28: 10000 | H28: 10000 | I28: 10000 | J28: 10000 | K28: 10000 | L28: 10000 | M28: 10000 | N28: 10000 | O28: 10000 | P28: 10000 | Q28: 10000 | R28: 10000 | S28: 10000 | T28: 10000 | U28: 10000 | V28: 10000 | W28: 10000 | X28: 10000 | Y28: 10000 | Z28: 10000 | AA28: 10000 | AB28: 10000 | AC28: 10000 | AD28: 10000 | AE28: 10000 | AF28: 10000 | AG28: 10000 | AH28: 10000 | AI28: 10000 | AJ28: 10000 | AK28: 10000 | AL28: 10000 | AM28: 10000 | AN28: 10000 | AO28: 10000 | AP28: 10000 | AQ28: 10000 | AR28: 10000 | AS28: 10000 | AT28: 10000 | AU28: 10000 | AV28: 10000 | AW28: 10000 | AX28: 10000 | AY28: 10000 | AZ28: 10000 | BA28: 10000 | BB28: 10000 | BC28: 10000 | BD28: 10000 | BE28: 10000 | BF28: 10000 | BG28: 10000 | BH28: 10000 | BI28: 10000 | BJ28: 10000
A29: Total | C29: =SUM(C12:C28) -> 214841.25 | D29: =SUM(D12:D28) -> 138644.65 | E29: =SUM(E12:E28) -> 138597.82 | F29: =SUM(F12:F28) -> 138839.9 | G29: =SUM(G12:G28) -> 138795.84 | H29: =SUM(H12:H28) -> 139960.6 | I29: =SUM(I12:I28) -> 140206.65 | J29: =SUM(J12:J28) -> 140166.44 | ... BJ29: =SUM(BJ12:BJ28) -> 339919.58
A31: Detail OPEX
A32: ='Financial Statements & Detail'!A109 -> Total Opening Subscribers-Cable | B32: ='Financial Statements & Detail'!B109 -> 0 | C32: ='Financial Statements & Detail'!C109 -> 11000 | D32: ='Financial Statements & Detail'!D109 -> 11220 | E32: ='Financial Statements & Detail'!E109 -> 11433.4 | F32: ='Financial Statements & Detail'!F109 -> 11640.398 | G32: ='Financial Statements & Detail'!G109 -> 11841.186 | H32: ='Financial Statements & Detail'!H109 -> 12035.95 | ... BJ32: ='Financial Statements & Detail'!BJ109 -> 79021.517
A34: Staffing
A35: Engineers Headend | C35: 9 | D35: 9 | E35: 9 | F35: 9 | G35: 9 | H35: 9 | I35: 9 | J35: 9 | K35: 9 | L35: 9 | M35: 9 | N35: 9 | O35: 9 | P35: 9 | Q35: 9 | R35: 9 | S35: 9 | T35: 9 | U35: 9 | V35: 9 | W35: 9 | X35: 9 | Y35: 9 | Z35: 9 | AA35: 9 | AB35: 9 | AC35: 9 | AD35: 9 | AE35: 9 | AF35: 9 | AG35: 9 | AH35: 9 | AI35: 9 | AJ35: 9 | AK35: 9 | AL35: 9 | AM35: 9 | AN35: 9 | AO35: 9 | AP35: 9 | AQ35: 9 | AR35: 9 | AS35: 9 | AT35: 9 | AU35: 9 | AV35: 9 | AW35: 9 | AX35: 9 | AY35: 9 | AZ35: 9 | BA35: 9 | BB35: 9 | BC35: 9 | BD35: 9 | BE35: 9 | BF35: 9 | BG35: 9 | BH35: 9 | BI35: 9 | BJ35: 9
A36: Salary per Month | C36: =4500/12 -> 375 | D36: =4500/12 -> 375 | E36: =4500/12 -> 375 | F36: =4500/12 -> 375 | G36: =4500/12 -> 375 | H36: =4500/12 -> 375 | I36: =4500/12 -> 375 | J36: =4500/12 -> 375 | ... BJ36: =4500/12 -> 375
A37: Cost | C37: =C35*C36 -> 3375 | D37: =D35*D36 -> 3375 | E37: =E35*E36 -> 3375 | F37: =F35*F36 -> 3375 | G37: =G35*G36 -> 3375 | H37: =H35*H36 -> 3375 | I37: =I35*I36 -> 3375 | J37: =J35*J36 -> 3375 | ... BJ37: =BJ35*BJ36 -> 3375
A39: Field Techs | C39: =ROUNDUP(C32/550,0) -> 20 | D39: =ROUNDUP(D32/550,0) -> 21 | E39: =ROUNDUP(E32/550,0) -> 21 | F39: =ROUNDUP(F32/550,0) -> 22 | G39: =ROUNDUP(G32/550,0) -> 22 | H39: =ROUNDUP(H32/550,0) -> 22 | I39: =ROUNDUP(I32/550,0) -> 23 | J39: =ROUNDUP(J32/550,0) -> 23 | ... BJ39: =ROUNDUP(BJ32/550,0) -> 144
A40: Salary per Month | C40: =3000/12 -> 250 | D40: =3000/12 -> 250 | E40: =3000/12 -> 250 | F40: =3000/12 -> 250 | G40: =3000/12 -> 250 | H40: =3000/12 -> 250 | I40: =3000/12 -> 250 | J40: =3000/12 -> 250 | ... BJ40: =3000/12 -> 250
A41: Cost | C41: =C39*C40 -> 5000 | D41: =D39*D40 -> 5250 | E41: =E39*E40 -> 5250 | F41: =F39*F40 -> 5500 | G41: =G39*G40 -> 5500 | H41: =H39*H40 -> 5500 | I41: =I39*I40 -> 5750 | J41: =J39*J40 -> 5750 | ... BJ41: =BJ39*BJ40 -> 36000
A43: Customer Service | C43: =ROUNDUP(C32/2000,0) -> 6 | D43: =ROUNDUP(D32/2000,0) -> 6 | E43: =ROUNDUP(E32/2000,0) -> 6 | F43: =ROUNDUP(F32/2000,0) -> 6 | G43: =ROUNDUP(G32/2000,0) -> 6 | H43: =ROUNDUP(H32/2000,0) -> 7 | I43: =ROUNDUP(I32/2000,0) -> 7 | J43: =ROUNDUP(J32/2000,0) -> 7 | ... BJ43: =ROUNDUP(BJ32/2000,0) -> 40
A44: Salary per Month | C44: 200 | D44: 200 | E44: 200 | F44: 200 | G44: 200 | H44: 200 | I44: 200 | J44: 200 | K44: 200 | L44: 200 | M44: 200 | N44: 200 | O44: 200 | P44: 200 | Q44: 200 | R44: 200 | S44: 200 | T44: 200 | U44: 200 | V44: 200 | W44: 200 | X44: 200 | Y44: 200 | Z44: 200 | AA44: 200 | AB44: 200 | AC44: 200 | AD44: 200 | AE44: 200 | AF44: 200 | AG44: 200 | AH44: 200 | AI44: 200 | AJ44: 200 | AK44: 200 | AL44: 200 | AM44: 200 | AN44: 200 | AO44: 200 | AP44: 200 | AQ44: 200 | AR44: 200 | AS44: 200 | AT44: 200 | AU44: 200 | AV44: 200 | AW44: 200 | AX44: 200 | AY44: 200 | AZ44: 200 | BA44: 200 | BB44: 200 | BC44: 200 | BD44: 200 | BE44: 200 | BF44: 200 | BG44: 200 | BH44: 200 | BI44: 200 | BJ44: 200
A45: Cost | C45: =C43*C44 -> 1200 | D45: =D43*D44 -> 1200 | E45: =E43*E44 -> 1200 | F45: =F43*F44 -> 1200 | G45: =G43*G44 -> 1200 | H45: =H43*H44 -> 1400 | I45: =I43*I44 -> 1400 | J45: =J43*J44 -> 1400 | ... BJ45: =BJ43*BJ44 -> 8000
A47: Lab Testing | C47: 8 | D47: 8 | E47: 8 | F47: 8 | G47: 8 | H47: 8 | I47: 8 | J47: 8 | K47: 8 | L47: 8 | M47: 8 | N47: 8 | O47: 8 | P47: 8 | Q47: 8 | R47: 8 | S47: 8 | T47: 8 | U47: 8 | V47: 8 | W47: 8 | X47: 8 | Y47: 8 | Z47: 8 | AA47: 8 | AB47: 8 | AC47: 8 | AD47: 8 | AE47: 8 | AF47: 8 | AG47: 8 | AH47: 8 | AI47: 8 | AJ47: 8 | AK47: 8 | AL47: 8 | AM47: 8 | AN47: 8 | AO47: 8 | AP47: 8 | AQ47: 8 | AR47: 8 | AS47: 8 | AT47: 8 | AU47: 8 | AV47: 8 | AW47: 8 | AX47: 8 | AY47: 8 | AZ47: 8 | BA47: 8 | BB47: 8 | BC47: 8 | BD47: 8 | BE47: 8 | BF47: 8 | BG47: 8 | BH47: 8 | BI47: 8 | BJ47: 8
A48: Salary per Month | C48: 200 | D48: 200 | E48: 200 | F48: 200 | G48: 200 | H48: 200 | I48: 200 | J48: 200 | K48: 200 | L48: 200 | M48: 200 | N48: 200 | O48: 200 | P48: 200 | Q48: 200 | R48: 200 | S48: 200 | T48: 200 | U48: 200 | V48: 200 | W48: 200 | X48: 200 | Y48: 200 | Z48: 200 | AA48: 200 | AB48: 200 | AC48: 200 | AD48: 200 | AE48: 200 | AF48: 200 | AG48: 200 | AH48: 200 | AI48: 200 | AJ48: 200 | AK48: 200 | AL48: 200 | AM48: 200 | AN48: 200 | AO48: 200 | AP48: 200 | AQ48: 200 | AR48: 200 | AS48: 200 | AT48: 200 | AU48: 200 | AV48: 200 | AW48: 200 | AX48: 200 | AY48: 200 | AZ48: 200 | BA48: 200 | BB48: 200 | BC48: 200 | BD48: 200 | BE48: 200 | BF48: 200 | BG48: 200 | BH48: 200 | BI48: 200 | BJ48: 200
A49: Cost | C49: =C47*C48 -> 1600 | D49: =D47*D48 -> 1600 | E49: =E47*E48 -> 1600 | F49: =F47*F48 -> 1600 | G49: =G47*G48 -> 1600 | H49: =H47*H48 -> 1600 | I49: =I47*I48 -> 1600 | J49: =J47*J48 -> 1600 | ... BJ49: =BJ47*BJ48 -> 1600
A51: Accounting/Collections | C51: =ROUNDUP(C32/2000,0) -> 6 | D51: =ROUNDUP(D32/2000,0) -> 6 | E51: =ROUNDUP(E32/2000,0) -> 6 | F51: =ROUNDUP(F32/2000,0) -> 6 | G51: =ROUNDUP(G32/2000,0) -> 6 | H51: =ROUNDUP(H32/2000,0) -> 7 | I51: =ROUNDUP(I32/2000,0) -> 7 | J51: =ROUNDUP(J32/2000,0) -> 7 | ... BJ51: =ROUNDUP(BJ32/2000,0) -> 40
A52: Salary per Month | C52: 250 | D52: 250 | E52: 250 | F52: 250 | G52: 250 | H52: 250 | I52: 250 | J52: 250 | K52: 250 | L52: 250 | M52: 250 | N52: 250 | O52: 250 | P52: 250 | Q52: 250 | R52: 250 | S52: 250 | T52: 250 | U52: 250 | V52: 250 | W52: 250 | X52: 250 | Y52: 250 | Z52: 250 | AA52: 250 | AB52: 250 | AC52: 250 | AD52: 250 | AE52: 250 | AF52: 250 | AG52: 250 | AH52: 250 | AI52: 250 | AJ52: 250 | AK52: 250 | AL52: 250 | AM52: 250 | AN52: 250 | AO52: 250 | AP52: 250 | AQ52: 250 | AR52: 250 | AS52: 250 | AT52: 250 | AU52: 250 | AV52: 250 | AW52: 250 | AX52: 250 | AY52: 250 | AZ52: 250 | BA52: 250 | BB52: 250 | BC52: 250 | BD52: 250 | BE52: 250 | BF52: 250 | BG52: 250 | BH52: 250 | BI52: 250 | BJ52: 250
A53: Cost | C53: =C51*C52 -> 1500 | D53: =D51*D52 -> 1500 | E53: =E51*E52 -> 1500 | F53: =F51*F52 -> 1500 | G53: =G51*G52 -> 1500 | H53: =H51*H52 -> 1750 | I53: =I51*I52 -> 1750 | J53: =J51*J52 -> 1750 | ... BJ53: =BJ51*BJ52 -> 10000
A55: Miscellaneous | C55: 5 | D55: 5 | E55: 5 | F55: 5 | G55: 5 | H55: 5 | I55: 5 | J55: 5 | K55: 5 | L55: 5 | M55: 5 | N55: 5 | O55: 5 | P55: 5 | Q55: 5 | R55: 5 | S55: 5 | T55: 5 | U55: 5 | V55: 5 | W55: 5 | X55: 5 | Y55: 5 | Z55: 5 | AA55: 5 | AB55: 5 | AC55: 5 | AD55: 5 | AE55: 5 | AF55: 5 | AG55: 5 | AH55: 5 | AI55: 5 | AJ55: 5 | AK55: 5 | AL55: 5 | AM55: 5 | AN55: 5 | AO55: 5 | AP55: 5 | AQ55: 5 | AR55: 5 | AS55: 5 | AT55: 5 | AU55: 5 | AV55: 5 | AW55: 5 | AX55: 5 | AY55: 5 | AZ55: 5 | BA55: 5 | BB55: 5 | BC55: 5 | BD55: 5 | BE55: 5 | BF55: 5 | BG55: 5 | BH55: 5 | BI55: 5 | BJ55: 5
A56: Salary per Month | C56: 200 | D56: 200 | E56: 200 | F56: 200 | G56: 200 | H56: 200 | I56: 200 | J56: 200 | K56: 200 | L56: 200 | M56: 200 | N56: 200 | O56: 200 | P56: 200 | Q56: 200 | R56: 200 | S56: 200 | T56: 200 | U56: 200 | V56: 200 | W56: 200 | X56: 200 | Y56: 200 | Z56: 200 | AA56: 200 | AB56: 200 | AC56: 200 | AD56: 200 | AE56: 200 | AF56: 200 | AG56: 200 | AH56: 200 | AI56: 200 | AJ56: 200 | AK56: 200 | AL56: 200 | AM56: 200 | AN56: 200 | AO56: 200 | AP56: 200 | AQ56: 200 | AR56: 200 | AS56: 200 | AT56: 200 | AU56: 200 | AV56: 200 | AW56: 200 | AX56: 200 | AY56: 200 | AZ56: 200 | BA56: 200 | BB56: 200 | BC56: 200 | BD56: 200 | BE56: 200 | BF56: 200 | BG56: 200 | BH56: 200 | BI56: 200 | BJ56: 200
A57: Cost | C57: =C55*C56 -> 1000 | D57: =D55*D56 -> 1000 | E57: =E55*E56 -> 1000 | F57: =F55*F56 -> 1000 | G57: =G55*G56 -> 1000 | H57: =H55*H56 -> 1000 | I57: =I55*I56 -> 1000 | J57: =J55*J56 -> 1000 | ... BJ57: =BJ55*BJ56 -> 1000
A59: Sales | C59: =ROUNDUP(MAX(C32/4000,B59),0) -> 3 | D59: =ROUNDUP(MAX(D32/4000,C59),0) -> 3 | E59: =ROUNDUP(MAX(E32/4000,D59),0) -> 3 | F59: =ROUNDUP(MAX(F32/4000,E59),0) -> 3 | G59: =ROUNDUP(MAX(G32/4000,F59),0) -> 3 | H59: =ROUNDUP(MAX(H32/4000,G59),0) -> 4 | I59: =ROUNDUP(MAX(I32/4000,H59),0) -> 4 | J59: =ROUNDUP(MAX(J32/4000,I59),0) -> 4 | ... BJ59: =ROUNDUP(MAX(BJ32/4000,BI59),0) -> 21
A60: Salary per Month | C60: 600 | D60: 600 | E60: 600 | F60: 600 | G60: 600 | H60: 600 | I60: 600 | J60: 600 | K60: 600 | L60: 600 | M60: 600 | N60: 600 | O60: 600 | P60: 600 | Q60: 600 | R60: 600 | S60: 600 | T60: 600 | U60: 600 | V60: 600 | W60: 600 | X60: 600 | Y60: 600 | Z60: 600 | AA60: 600 | AB60: 600 | AC60: 600 | AD60: 600 | AE60: 600 | AF60: 600 | AG60: 600 | AH60: 600 | AI60: 600 | AJ60: 600 | AK60: 600 | AL60: 600 | AM60: 600 | AN60: 600 | AO60: 600 | AP60: 600 | AQ60: 600 | AR60: 600 | AS60: 600 | AT60: 600 | AU60: 600 | AV60: 600 | AW60: 600 | AX60: 600 | AY60: 600 | AZ60: 600 | BA60: 600 | BB60: 600 | BC60: 600 | BD60: 600 | BE60: 600 | BF60: 600 | BG60: 600 | BH60: 600 | BI60: 600 | BJ60: 600
A61: Cost | C61: =C59*C60 -> 1800 | D61: =D59*D60 -> 1800 | E61: =E59*E60 -> 1800 | F61: =F59*F60 -> 1800 | G61: =G59*G60 -> 1800 | H61: =H59*H60 -> 2400 | I61: =I59*I60 -> 2400 | J61: =J59*J60 -> 2400 | ... BJ61: =BJ59*BJ60 -> 12600
A63: Staff Headcount Total | C63: =C35+C39+C43+C47+C51+C55+C59 -> 57 | D63: =D35+D39+D43+D47+D51+D55+D59 -> 58 | E63: =E35+E39+E43+E47+E51+E55+E59 -> 58 | F63: =F35+F39+F43+F47+F51+F55+F59 -> 59 | G63: =G35+G39+G43+G47+G51+G55+G59 -> 59 | H63: =H35+H39+H43+H47+H51+H55+H59 -> 62 | I63: =I35+I39+I43+I47+I51+I55+I59 -> 63 | J63: =J35+J39+J43+J47+J51+J55+J59 -> 63 | ... BJ63: =BJ35+BJ39+BJ43+BJ47+BJ51+BJ55+BJ59 -> 267
A65: Management | B65: Annual
A66: CEO | B66: 350000 | C66: =$B66/12 -> 29166.667 | D66: =$B66/12 -> 29166.667 | E66: =$B66/12 -> 29166.667 | F66: =$B66/12 -> 29166.667 | G66: =$B66/12 -> 29166.667 | H66: =$B66/12 -> 29166.667 | I66: =$B66/12 -> 29166.667 | J66: =$B66/12 -> 29166.667 | ... BJ66: =$B66/12 -> 29166.667
A67: CTO | B67: 200000 | C67: =$B67/12 -> 16666.667 | D67: =$B67/12 -> 16666.667 | E67: =$B67/12 -> 16666.667 | F67: =$B67/12 -> 16666.667 | G67: =$B67/12 -> 16666.667 | H67: =$B67/12 -> 16666.667 | I67: =$B67/12 -> 16666.667 | J67: =$B67/12 -> 16666.667 | ... BJ67: =$B67/12 -> 16666.667
A68: Controller | B68: 80000 | C68: =$B68/12 -> 6666.6667 | D68: =$B68/12 -> 6666.6667 | E68: =$B68/12 -> 6666.6667 | F68: =$B68/12 -> 6666.6667 | G68: =$B68/12 -> 6666.6667 | H68: =$B68/12 -> 6666.6667 | I68: =$B68/12 -> 6666.6667 | J68: =$B68/12 -> 6666.6667 | ... BJ68: =$B68/12 -> 6666.6667
A69: Marketing | B69: 100000 | C69: =$B69/12 -> 8333.3333 | D69: =$B69/12 -> 8333.3333 | E69: =$B69/12 -> 8333.3333 | F69: =$B69/12 -> 8333.3333 | G69: =$B69/12 -> 8333.3333 | H69: =$B69/12 -> 8333.3333 | I69: =$B69/12 -> 8333.3333 | J69: =$B69/12 -> 8333.3333 | ... BJ69: =$B69/12 -> 8333.3333
A70: General Manager | B70: 100000 | C70: =$B70/12 -> 8333.3333 | D70: =$B70/12 -> 8333.3333 | E70: =$B70/12 -> 8333.3333 | F70: =$B70/12 -> 8333.3333 | G70: =$B70/12 -> 8333.3333 | H70: =$B70/12 -> 8333.3333 | I70: =$B70/12 -> 8333.3333 | J70: =$B70/12 -> 8333.3333 | ... BJ70: =$B70/12 -> 8333.3333
A71: Govt. Relations | B71: 100000 | C71: =$B71/12 -> 8333.3333 | D71: =$B71/12 -> 8333.3333 | E71: =$B71/12 -> 8333.3333 | F71: =$B71/12 -> 8333.3333 | G71: =$B71/12 -> 8333.3333 | H71: =$B71/12 -> 8333.3333 | I71: =$B71/12 -> 8333.3333 | J71: =$B71/12 -> 8333.3333 | ... BJ71: =$B71/12 -> 8333.3333
A72: Sales Manager | B72: 70000 | C72: =IF(C59>8,$B72/12,0) -> 0 | D72: =IF(D59>8,$B72/12,0) -> 0 | E72: =IF(E59>8,$B72/12,0) -> 0 | F72: =IF(F59>8,$B72/12,0) -> 0 | G72: =IF(G59>8,$B72/12,0) -> 0 | H72: =IF(H59>8,$B72/12,0) -> 0 | I72: =IF(I59>8,$B72/12,0) -> 0 | J72: =IF(J59>8,$B72/12,0) -> 0 | ... BJ72: =IF(BJ59>8,$B72/12,0) -> 5833.3333
A73: Collections Manager | B73: 35000 | C73: =IF(C51>10,$B$73/12,0) -> 0 | D73: =IF(D51>10,$B$73/12,0) -> 0 | E73: =IF(E51>10,$B$73/12,0) -> 0 | F73: =IF(F51>10,$B$73/12,0) -> 0 | G73: =IF(G51>10,$B$73/12,0) -> 0 | H73: =IF(H51>10,$B$73/12,0) -> 0 | I73: =IF(I51>10,$B$73/12,0) -> 0 | J73: =IF(J51>10,$B$73/12,0) -> 0 | ... BJ73: =IF(BJ51>10,$B$73/12,0) -> 2916.6667
A74: Customer Service Manager | B74: 50000 | C74: =IF(C43>10,$B$74/12,0) -> 0 | D74: =IF(D43>10,$B$74/12,0) -> 0 | E74: =IF(E43>10,$B$74/12,0) -> 0 | F74: =IF(F43>10,$B$74/12,0) -> 0 | G74: =IF(G43>10,$B$74/12,0) -> 0 | H74: =IF(H43>10,$B$74/12,0) -> 0 | I74: =IF(I43>10,$B$74/12,0) -> 0 | J74: =IF(J43>10,$B$74/12,0) -> 0 | ... BJ74: =IF(BJ43>10,$B$74/12,0) -> 4166.6667
A75: Total Management | C75: =SUM(C66:C74) -> 77500 | D75: =SUM(D66:D74) -> 77500 | E75: =SUM(E66:E74) -> 77500 | F75: =SUM(F66:F74) -> 77500 | G75: =SUM(G66:G74) -> 77500 | H75: =SUM(H66:H74) -> 77500 | I75: =SUM(I66:I74) -> 77500 | J75: =SUM(J66:J74) -> 77500 | ... BJ75: =SUM(BJ66:BJ74) -> 90416.667
A77: Grand Total Salaries | C77: =C37+C41+C45+C49+C53+C57+C61+C75 -> 92975 | D77: =D37+D41+D45+D49+D53+D57+D61+D75 -> 93225 | E77: =E37+E41+E45+E49+E53+E57+E61+E75 -> 93225 | F77: =F37+F41+F45+F49+F53+F57+F61+F75 -> 93475 | G77: =G37+G41+G45+G49+G53+G57+G61+G75 -> 93475 | H77: =H37+H41+H45+H49+H53+H57+H61+H75 -> 94525 | I77: =I37+I41+I45+I49+I53+I57+I61+I75 -> 94775 | J77: =J37+J41+J45+J49+J53+J57+J61+J75 -> 94775 | ... BJ77: =BJ37+BJ41+BJ45+BJ49+BJ53+BJ57+BJ61+BJ75 -> 162991.67
A79: Benefits | B79: 0.15 | C79: =$B$79*C77 -> 13946.25 | D79: =$B$79*D77 -> 13983.75 | E79: =$B$79*E77 -> 13983.75 | F79: =$B$79*F77 -> 14021.25 | G79: =$B$79*G77 -> 14021.25 | H79: =$B$79*H77 -> 14178.75 | I79: =$B$79*I77 -> 14216.25 | J79: =$B$79*J77 -> 14216.25 | ... BJ79: =$B$79*BJ77 -> 24448.75
A81: Commissions Sales and Collections | B81: 0.03 | C81: =$B$81*'Financial Statements & Detail'!C123 -> 14185.05 | D81: =$B$81*'Financial Statements & Detail'!D123 -> 14468.751 | E81: =$B$81*'Financial Statements & Detail'!E123 -> 14743.941 | F81: =$B$81*'Financial Statements & Detail'!F123 -> 15010.875 | G81: =$B$81*'Financial Statements & Detail'!G123 -> 15269.801 | H81: =$B$81*'Financial Statements & Detail'!H123 -> 15520.96 | I81: =$B$81*'Financial Statements & Detail'!I123 -> 15764.584 | J81: =$B$81*'Financial Statements & Detail'!J123 -> 16000.899 | ... BJ81: =$B$81*'Financial Statements & Detail'!BJ123 -> 101902.2
A83: Insurance | B83: 7 | C83: =$B$83*C63 -> 399 | D83: =$B$83*D63 -> 406 | E83: =$B$83*E63 -> 406 | F83: =$B$83*F63 -> 413 | G83: =$B$83*G63 -> 413 | H83: =$B$83*H63 -> 434 | I83: =$B$83*I63 -> 441 | J83: =$B$83*J63 -> 441 | ... BJ83: =$B$83*BJ63 -> 1869
A85: Uniforms | B85: 2 | C85: =$B$85*C63 -> 114 | D85: =$B$85*D63 -> 116 | E85: =$B$85*E63 -> 116 | F85: =$B$85*F63 -> 118 | G85: =$B$85*G63 -> 118 | H85: =$B$85*H63 -> 124 | I85: =$B$85*I63 -> 126 | J85: =$B$85*J63 -> 126 | ... BJ85: =$B$85*BJ63 -> 534
A87: Fuel, Auto, Repairs | C87: 15000 | D87: =C87 -> 15000 | E87: =D87 -> 15000 | F87: =E87 -> 15000 | G87: =F87 -> 15000 | H87: =G87 -> 15000 | I87: =H87 -> 15000 | J87: =I87 -> 15000 | K87: =J87 -> 15000 | ... BJ87: =BI87 -> 15000
A89: Customer Acquisition Cost
A90: Cable
A91: New subs | C91: ='Financial Statements & Detail'!C105 -> 275 | D91: ='Financial Statements & Detail'!D105 -> 275 | E91: ='Financial Statements & Detail'!E105 -> 275 | F91: ='Financial Statements & Detail'!F105 -> 275 | G91: ='Financial Statements & Detail'!G105 -> 275 | H91: ='Financial Statements & Detail'!H105 -> 275 | I91: ='Financial Statements & Detail'!I105 -> 275 | J91: ='Financial Statements & Detail'!J105 -> 275 | ... BJ91: ='Financial Statements & Detail'!BJ105 -> 1433.3333
A92: Cost | C92: =Cable_Customer_Acquisition_Cost*OPEX!C91 -> 1375 | D92: =Cable_Customer_Acquisition_Cost*OPEX!D91 -> 1375 | E92: =Cable_Customer_Acquisition_Cost*OPEX!E91 -> 1375 | F92: =Cable_Customer_Acquisition_Cost*OPEX!F91 -> 1375 | G92: =Cable_Customer_Acquisition_Cost*OPEX!G91 -> 1375 | H92: =Cable_Customer_Acquisition_Cost*OPEX!H91 -> 1375 | I92: =Cable_Customer_Acquisition_Cost*OPEX!I91 -> 1375 | J92: =Cable_Customer_Acquisition_Cost*OPEX!J91 -> 1375 | ... BJ92: =Cable_Customer_Acquisition_Cost*OPEX!BJ91 -> 7166.6667
A93: Voice
A94: New subs | C94: =MAX('Financial Statements & Detail'!C115-'Financial Statements & Detail'!B115,0) -> 4826.25 | D94: =MAX('Financial Statements & Detail'!D115-'Financial Statements & Detail'!C115,0) -> 96.525 | E94: =MAX('Financial Statements & Detail'!E115-'Financial Statements & Detail'!D115,0) -> 93.62925 | F94: =MAX('Financial Statements & Detail'!F115-'Financial Statements & Detail'!E115,0) -> 90.820373 | G94: =MAX('Financial Statements & Detail'!G115-'Financial Statements & Detail'!F115,0) -> 88.095761 | H94: =MAX('Financial Statements & Detail'!H115-'Financial Statements & Detail'!G115,0) -> 85.452888 | I94: =MAX('Financial Statements & Detail'!I115-'Financial Statements & Detail'!H115,0) -> 82.889302 | J94: =MAX('Financial Statements & Detail'!J115-'Financial Statements & Detail'!I115,0) -> 80.402623 | ... BJ94: =MAX('Financial Statements & Detail'!BJ115-'Financial Statements & Detail'!BI115,0) -> 0
A95: Cost | C95: =C94*Voice_Customer_Acquisition_cost -> 48262.5 | D95: =D94*Voice_Customer_Acquisition_cost -> 965.25 | E95: =E94*Voice_Customer_Acquisition_cost -> 936.2925 | F95: =F94*Voice_Customer_Acquisition_cost -> 908.20373 | G95: =G94*Voice_Customer_Acquisition_cost -> 880.95761 | H95: =H94*Voice_Customer_Acquisition_cost -> 854.52888 | I95: =I94*Voice_Customer_Acquisition_cost -> 828.89302 | J95: =J94*Voice_Customer_Acquisition_cost -> 804.02623 | ... BJ95: =BJ94*Voice_Customer_Acquisition_cost -> 0
A96: Data
A97: New subs | C97: =MAX('Financial Statements & Detail'!C116-'Financial Statements & Detail'!B116,0) -> 5956.5 | D97: =MAX('Financial Statements & Detail'!D116-'Financial Statements & Detail'!C116,0) -> 119.13 | E97: =MAX('Financial Statements & Detail'!E116-'Financial Statements & Detail'!D116,0) -> 115.5561 | F97: =MAX('Financial Statements & Detail'!F116-'Financial Statements & Detail'!E116,0) -> 112.08942 | G97: =MAX('Financial Statements & Detail'!G116-'Financial Statements & Detail'!F116,0) -> 108.72673 | H97: =MAX('Financial Statements & Detail'!H116-'Financial Statements & Detail'!G116,0) -> 105.46493 | I97: =MAX('Financial Statements & Detail'!I116-'Financial Statements & Detail'!H116,0) -> 102.30098 | J97: =MAX('Financial Statements & Detail'!J116-'Financial Statements & Detail'!I116,0) -> 99.231955 | ... BJ97: =MAX('Financial Statements & Detail'!BJ116-'Financial Statements & Detail'!BI116,0) -> 0
A98: Cost | C98: =C97*Data_Customer_Acquisition_cost -> 29782.5 | D98: =D97*Data_Customer_Acquisition_cost -> 595.65 | E98: =E97*Data_Customer_Acquisition_cost -> 577.7805 | F98: =F97*Data_Customer_Acquisition_cost -> 560.44709 | G98: =G97*Data_Customer_Acquisition_cost -> 543.63367 | H98: =H97*Data_Customer_Acquisition_cost -> 527.32466 | I98: =I97*Data_Customer_Acquisition_cost -> 511.50492 | J98: =J97*Data_Customer_Acquisition_cost -> 496.15977 | ... BJ98: =BJ97*Data_Customer_Acquisition_cost -> 0
A99: Total Acquisition Cost | C99: =C92+C95+C98 -> 79420 | D99: =D92+D95+D98 -> 2935.9 | E99: =E92+E95+E98 -> 2889.073 | F99: =F92+F95+F98 -> 2843.6508 | G99: =G92+G95+G98 -> 2799.5913 | H99: =H92+H95+H98 -> 2756.8535 | I99: =I92+I95+I98 -> 2715.3979 | J99: =J92+J95+J98 -> 2675.186 | ... BJ99: =BJ92+BJ95+BJ98 -> 7166.6667
A101: Professional Fees | B101: 2000 | C101: =B101 -> 2000 | D101: =C101 -> 2000 | E101: =D101 -> 2000 | F101: =E101 -> 2000 | G101: =F101 -> 2000 | H101: =G101 -> 2000 | I101: =H101 -> 2000 | J101: =I101 -> 2000 | ... N101: =M101 -> 2000 | O101: =C101+1000 -> 3000 | P101: =D101+1000 -> 3000 | Q101: =E101+1000 -> 3000 | R101: =F101+1000 -> 3000 | S101: =G101+1000 -> 3000 | T101: =H101+1000 -> 3000 | U101: =I101+1000 -> 3000 | V101: =J101+1000 -> 3000 | ... BJ101: =AX101+1000 -> 6000
A102: Travel | B102: 5000 | C102: =B102 -> 5000 | D102: =C102 -> 5000 | E102: =D102 -> 5000 | F102: =E102 -> 5000 | G102: =F102 -> 5000 | H102: =G102 -> 5000 | I102: =H102 -> 5000 | J102: =I102 -> 5000 | ... N102: =M102 -> 5000 | O102: =C102*1.5 -> 7500 | P102: =D102*1.5 -> 7500 | Q102: =E102*1.5 -> 7500 | R102: =F102*1.5 -> 7500 | S102: =G102*1.5 -> 7500 | T102: =H102*1.5 -> 7500 | U102: =I102*1.5 -> 7500 | V102: =J102*1.5 -> 7500 | ... BJ102: =AX102*1.5 -> 25312.5
A103: Insurance Property-?? | B103: 0 | C103: =B103 -> 0 | D103: =C103 -> 0 | E103: =D103 -> 0 | F103: =E103 -> 0 | G103: =F103 -> 0 | H103: =G103 -> 0 | I103: =H103 -> 0 | J103: =I103 -> 0 | ... BJ103: =BI103 -> 0
A104: Office Rent | B104: 10000 | C104: =B104 -> 10000 | D104: =C104 -> 10000 | E104: =D104 -> 10000 | F104: =E104 -> 10000 | G104: =F104 -> 10000 | H104: =G104 -> 10000 | I104: =H104 -> 10000 | J104: =I104 -> 10000 | ... Z104: =Y104 -> 10000 | AA104: =O104*2 -> 20000 | AB104: =P104*2 -> 20000 | AC104: =Q104*2 -> 20000 | AD104: =R104*2 -> 20000 | AE104: =S104*2 -> 20000 | AF104: =T104*2 -> 20000 | AG104: =U104*2 -> 20000 | AH104: =V104*2 -> 20000 | ... BJ104: =AX104*2 -> 80000
A105: Office Supplies | B105: 1500 | C105: =B105 -> 1500 | D105: =C105 -> 1500 | E105: =D105 -> 1500 | F105: =E105 -> 1500 | G105: =F105 -> 1500 | H105: =G105 -> 1500 | I105: =H105 -> 1500 | J105: =I105 -> 1500 | ... N105: =M105 -> 1500 | O105: =C105*2 -> 3000 | P105: =D105*2 -> 3000 | Q105: =E105*2 -> 3000 | R105: =F105*2 -> 3000 | S105: =G105*2 -> 3000 | T105: =H105*2 -> 3000 | U105: =I105*2 -> 3000 | V105: =J105*2 -> 3000 | ... BJ105: =AX105*2 -> 24000

Sheet Sheet6

Sheet Sheet7

Sheet Sheet8
